[{"Key":"Key","日期":"日期","科目":"科目","項目":"項目","金額":"金額","備註1":"備註1","備註2":"備註2","編輯":"編輯"},{"Key":"3066","日期":"2014-03-24","科目":"1.現收","項目":"AE","金額":"8370","備註1":"3/28","備註2":"8148","編輯":""},{"Key":"3044","日期":"2014-03-22","科目":"1.現收","項目":"AE","金額":"9300","備註1":"3/27","備註2":"9026","編輯":""},{"Key":"2976","日期":"2014-03-16","科目":"1.現收","項目":"AE","金額":"10400","備註1":"3/21","備註2":"10064","編輯":""},{"Key":"2924","日期":"2014-03-09","科目":"1.現收","項目":"AE","金額":"3200","備註1":"3/14","備註2":"3106","編輯":""},{"Key":"3146","日期":"2014-03-31","科目":"1.現收","項目":"分3期","金額":"16000","備註1":"4/7","備註2":"15711","編輯":""},{"Key":"3141","日期":"2014-03-30","科目":"1.現收","項目":"分3期","金額":"44800","備註1":"4/7","備註2":"43590","編輯":""},{"Key":"3095","日期":"2014-03-25","科目":"1.現收","項目":"分3期","金額":"16900","備註1":"3/31","備註2":"16478","編輯":""},{"Key":"3054","日期":"2014-03-23","科目":"1.現收","項目":"分3期","金額":"12000","備註1":"3/28","備註2":"11676","編輯":""},{"Key":"3032","日期":"2014-03-20","科目":"1.現收","項目":"分3期","金額":"3200","備註1":"3/25","備註2":"3120","編輯":""},{"Key":"3010","日期":"2014-03-18","科目":"1.現收","項目":"分3期","金額":"4850","備註1":"3/24","備註2":"4729","編輯":""},{"Key":"2970","日期":"2014-03-15","科目":"1.現收","項目":"分3期","金額":"6900","備註1":"3/20","備註2":"6728","編輯":""},{"Key":"2961","日期":"2014-03-14","科目":"1.現收","項目":"分3期","金額":"14850","備註1":"3/20","備註2":"14478","編輯":""},{"Key":"2943","日期":"2014-03-12","科目":"1.現收","項目":"分3期","金額":"44000","備註1":"3/18","備註2":"43032","編輯":""},{"Key":"2894","日期":"2014-03-08","科目":"1.現收","項目":"分3期","金額":"6950","備註1":"3/13","備註2":"6798","編輯":""},{"Key":"2862","日期":"2014-03-04","科目":"1.現收","項目":"分3期","金額":"2800","備註1":"3/10","備註2":"2731","編輯":""},{"Key":"2847","日期":"2014-03-03","科目":"1.現收","項目":"分3期","金額":"15300","備註1":"3/7","備註2":"14964","編輯":""},{"Key":"3145","日期":"2014-03-31","科目":"1.現收","項目":"刷卡(V-M-J-銀)","金額":"29000","備註1":"4/7","備註2":"28420","編輯":""},{"Key":"3140","日期":"2014-03-30","科目":"1.現收","項目":"刷卡(V-M-J-銀)","金額":"41050","備註1":"4/7","備註2":"40229","編輯":""},{"Key":"3136","日期":"2014-03-29","科目":"1.現收","項目":"刷卡(V-M-J-銀)","金額":"33400","備註1":"4/3","備註2":"32732","編輯":""},{"Key":"3128","日期":"2014-03-28","科目":"1.現收","項目":"刷卡(V-M-J-銀)","金額":"64200","備註1":"4/3","備註2":"62916","編輯":""},{"Key":"3117","日期":"2014-03-27","科目":"1.現收","項目":"刷卡(V-M-J-銀)","金額":"15400","備註1":"4/2","備註2":"15092","編輯":""},{"Key":"3109","日期":"2014-03-26","科目":"1.現收","項目":"刷卡(V-M-J-銀)","金額":"64200","備註1":"4/1","備註2":"62916","編輯":""},{"Key":"3094","日期":"2014-03-25","科目":"1.現收","項目":"刷卡(V-M-J-銀)","金額":"5500","備註1":"3/31","備註2":"5390","編輯":""},{"Key":"3065","日期":"2014-03-24","科目":"1.現收","項目":"刷卡(V-M-J-銀)","金額":"62850","備註1":"3/28","備註2":"61593","編輯":""},{"Key":"3053","日期":"2014-03-23","科目":"1.現收","項目":"刷卡(V-M-J-銀)","金額":"6900","備註1":"3/28","備註2":"6762","編輯":""},{"Key":"3043","日期":"2014-03-22","科目":"1.現收","項目":"刷卡(V-M-J-銀)","金額":"68020","備註1":"3/27","備註2":"66660","編輯":""},{"Key":"3038","日期":"2014-03-21","科目":"1.現收","項目":"刷卡(V-M-J-銀)","金額":"57200","備註1":"3/27","備註2":"56056","編輯":""},{"Key":"3031","日期":"2014-03-20","科目":"1.現收","項目":"刷卡(V-M-J-銀)","金額":"15800","備註1":"3/26","備註2":"15484","編輯":""},{"Key":"3025","日期":"2014-03-19","科目":"1.現收","項目":"刷卡(V-M-J-銀)","金額":"2330","備註1":"3/25","備註2":"2284","編輯":""},{"Key":"3009","日期":"2014-03-18","科目":"1.現收","項目":"刷卡(V-M-J-銀)","金額":"48690","備註1":"3/24","備註2":"47717","編輯":""},{"Key":"2982","日期":"2014-03-17","科目":"1.現收","項目":"刷卡(V-M-J-銀)","金額":"13050","備註1":"3/21","備註2":"12789","編輯":""},{"Key":"2975","日期":"2014-03-16","科目":"1.現收","項目":"刷卡(V-M-J-銀)","金額":"27790","備註1":"3/21","備註2":"27235","編輯":""},{"Key":"2969","日期":"2014-03-15","科目":"1.現收","項目":"刷卡(V-M-J-銀)","金額":"50800","備註1":"3/20","備註2":"49784","編輯":""},{"Key":"2960","日期":"2014-03-14","科目":"1.現收","項目":"刷卡(V-M-J-銀)","金額":"1850","備註1":"3/20","備註2":"1813","編輯":""},{"Key":"2953","日期":"2014-03-13","科目":"1.現收","項目":"刷卡(V-M-J-銀)","金額":"7550","備註1":"3/19","備註2":"7399","編輯":""},{"Key":"2942","日期":"2014-03-12","科目":"1.現收","項目":"刷卡(V-M-J-銀)","金額":"550","備註1":"3/18","備註2":"539","編輯":""},{"Key":"2935","日期":"2014-03-11","科目":"1.現收","項目":"刷卡(V-M-J-銀)","金額":"4390","備註1":"3/17","備註2":"4303","編輯":""},{"Key":"2928","日期":"2014-03-10","科目":"1.現收","項目":"刷卡(V-M-J-銀)","金額":"23010","備註1":"3/14","備註2":"22550","編輯":""},{"Key":"2923","日期":"2014-03-09","科目":"1.現收","項目":"刷卡(V-M-J-銀)","金額":"45900","備註1":"3/14","備註2":"44982","編輯":""},{"Key":"2893","日期":"2014-03-08","科目":"1.現收","項目":"刷卡(V-M-J-銀)","金額":"68950","備註1":"3/13","備註2":"67571","編輯":""},{"Key":"2887","日期":"2014-03-07","科目":"1.現收","項目":"刷卡(V-M-J-銀)","金額":"39500","備註1":"3/13","備註2":"38710","編輯":""},{"Key":"2879","日期":"2014-03-06","科目":"1.現收","項目":"刷卡(V-M-J-銀)","金額":"6400","備註1":"3/12","備註2":"6272","編輯":""},{"Key":"2872","日期":"2014-03-05","科目":"1.現收","項目":"刷卡(V-M-J-銀)","金額":"22500","備註1":"3/11","備註2":"22050","編輯":""},{"Key":"2861","日期":"2014-03-04","科目":"1.現收","項目":"刷卡(V-M-J-銀)","金額":"40170","備註1":"3/10","備註2":"39367","編輯":""},{"Key":"2846","日期":"2014-03-03","科目":"1.現收","項目":"刷卡(V-M-J-銀)","金額":"48850","備註1":"3/7","備註2":"47873","編輯":""},{"Key":"2840","日期":"2014-03-02","科目":"1.現收","項目":"刷卡(V-M-J-銀)","金額":"29490","備註1":"3/7","備註2":"28901","編輯":""},{"Key":"2832","日期":"2014-03-01","科目":"1.現收","項目":"刷卡(V-M-J-銀)","金額":"56200","備註1":"3/6","備註2":"55076","編輯":""},{"Key":"3144","日期":"2014-03-31","科目":"1.現收","項目":"耳機現金","金額":"80712","備註1":"","備註2":"","編輯":""},{"Key":"3139","日期":"2014-03-30","科目":"1.現收","項目":"耳機現金","金額":"93871","備註1":"","備註2":"","編輯":""},{"Key":"3134","日期":"2014-03-29","科目":"1.現收","項目":"耳機現金","金額":"117747","備註1":"","備註2":"","編輯":""},{"Key":"3127","日期":"2014-03-28","科目":"1.現收","項目":"耳機現金","金額":"94573","備註1":"","備註2":"","編輯":""},{"Key":"3116","日期":"2014-03-27","科目":"1.現收","項目":"耳機現金","金額":"52600","備註1":"","備註2":"","編輯":""},{"Key":"3108","日期":"2014-03-26","科目":"1.現收","項目":"耳機現金","金額":"29990","備註1":"","備註2":"","編輯":""},{"Key":"3093","日期":"2014-03-25","科目":"1.現收","項目":"耳機現金","金額":"21790","備註1":"","備註2":"","編輯":""},{"Key":"3064","日期":"2014-03-24","科目":"1.現收","項目":"耳機現金","金額":"18828","備註1":"","備註2":"","編輯":""},{"Key":"3052","日期":"2014-03-23","科目":"1.現收","項目":"耳機現金","金額":"115540","備註1":"","備註2":"","編輯":""},{"Key":"3042","日期":"2014-03-22","科目":"1.現收","項目":"耳機現金","金額":"78308","備註1":"","備註2":"","編輯":""},{"Key":"3037","日期":"2014-03-21","科目":"1.現收","項目":"耳機現金","金額":"179270","備註1":"","備註2":"","編輯":""},{"Key":"3030","日期":"2014-03-20","科目":"1.現收","項目":"耳機現金","金額":"41034","備註1":"","備註2":"","編輯":""},{"Key":"3024","日期":"2014-03-19","科目":"1.現收","項目":"耳機現金","金額":"25415","備註1":"","備註2":"","編輯":""},{"Key":"3008","日期":"2014-03-18","科目":"1.現收","項目":"耳機現金","金額":"39600","備註1":"","備註2":"","編輯":""},{"Key":"2981","日期":"2014-03-17","科目":"1.現收","項目":"耳機現金","金額":"36025","備註1":"","備註2":"","編輯":""},{"Key":"2974","日期":"2014-03-16","科目":"1.現收","項目":"耳機現金","金額":"73830","備註1":"","備註2":"","編輯":""},{"Key":"2968","日期":"2014-03-15","科目":"1.現收","項目":"耳機現金","金額":"94470","備註1":"","備註2":"","編輯":""},{"Key":"2959","日期":"2014-03-14","科目":"1.現收","項目":"耳機現金","金額":"67684","備註1":"","備註2":"","編輯":""},{"Key":"2952","日期":"2014-03-13","科目":"1.現收","項目":"耳機現金","金額":"30742","備註1":"","備註2":"","編輯":""},{"Key":"2941","日期":"2014-03-12","科目":"1.現收","項目":"耳機現金","金額":"35015","備註1":"","備註2":"","編輯":""},{"Key":"2934","日期":"2014-03-11","科目":"1.現收","項目":"耳機現金","金額":"40232","備註1":"","備註2":"","編輯":""},{"Key":"2927","日期":"2014-03-10","科目":"1.現收","項目":"耳機現金","金額":"57337","備註1":"","備註2":"","編輯":""},{"Key":"2922","日期":"2014-03-09","科目":"1.現收","項目":"耳機現金","金額":"144874","備註1":"","備註2":"","編輯":""},{"Key":"2892","日期":"2014-03-08","科目":"1.現收","項目":"耳機現金","金額":"131563","備註1":"","備註2":"","編輯":""},{"Key":"2886","日期":"2014-03-07","科目":"1.現收","項目":"耳機現金","金額":"112087","備註1":"","備註2":"","編輯":""},{"Key":"2878","日期":"2014-03-06","科目":"1.現收","項目":"耳機現金","金額":"50868","備註1":"","備註2":"","編輯":""},{"Key":"2871","日期":"2014-03-05","科目":"1.現收","項目":"耳機現金","金額":"44195","備註1":"","備註2":"","編輯":""},{"Key":"2860","日期":"2014-03-04","科目":"1.現收","項目":"耳機現金","金額":"80891","備註1":"","備註2":"","編輯":""},{"Key":"2845","日期":"2014-03-03","科目":"1.現收","項目":"耳機現金","金額":"61950","備註1":"","備註2":"","編輯":""},{"Key":"2838","日期":"2014-03-02","科目":"1.現收","項目":"耳機現金","金額":"49952","備註1":"","備註2":"","編輯":""},{"Key":"2831","日期":"2014-03-01","科目":"1.現收","項目":"耳機現金","金額":"68120","備註1":"","備註2":"","編輯":""},{"Key":"3017","日期":"2014-03-18","科目":"2.票收","項目":"票收","金額":"5600","備註1":"赫柏","備註2":"華泰迪化街73617AB57768281030228","編輯":""},{"Key":"2973","日期":"2014-03-15","科目":"2.票收","項目":"票收","金額":"40","備註1":"國庫退稅","備註2":"中央銀行000267155AN59665491030220","編輯":""},{"Key":"2989","日期":"2014-03-17","科目":"3.銀收","項目":"富邦335","金額":"112","備註1":"定存利息","備註2":"","編輯":""},{"Key":"3090","日期":"2014-03-24","科目":"3.銀收","項目":"富邦408","金額":"28947","備註1":"好樂迪","備註2":"2014-1","編輯":""},{"Key":"3091","日期":"2014-03-24","科目":"3.銀收","項目":"富邦408","金額":"69632","備註1":"錢櫃","備註2":"2014-1","編輯":""},{"Key":"3414","日期":"2014-03-27","科目":"3.銀收","項目":"永豐854","金額":"66024","備註1":"露天","備註2":"網拍","編輯":""},{"Key":"3075","日期":"2014-03-21","科目":"3.銀收","項目":"永豐854","金額":"1050","備註1":"700030332843","備註2":"","編輯":""},{"Key":"3076","日期":"2014-03-21","科目":"3.銀收","項目":"永豐854","金額":"20","備註1":"利息","備註2":"2014-3","編輯":""},{"Key":"3077","日期":"2014-03-16","科目":"3.銀收","項目":"永豐854","金額":"14000","備註1":"017410111836","備註2":"B&WP7","編輯":""},{"Key":"3078","日期":"2014-03-11","科目":"3.銀收","項目":"永豐854","金額":"500","備註1":"捷孚凱行銷","備註2":"市調費","編輯":""},{"Key":"3079","日期":"2014-03-10","科目":"3.銀收","項目":"永豐854","金額":"5700","備註1":"013030004252","備註2":"","編輯":""},{"Key":"3080","日期":"2014-03-07","科目":"3.銀收","項目":"永豐854","金額":"5900","備註1":"700250755062","備註2":"","編輯":""},{"Key":"3081","日期":"2014-03-07","科目":"3.銀收","項目":"永豐854","金額":"37140","備註1":"宅急便代收","備註2":"334","編輯":""},{"Key":"3082","日期":"2014-03-05","科目":"3.銀收","項目":"永豐854","金額":"8100","備註1":"008200277964","備註2":"","編輯":""},{"Key":"3083","日期":"2014-03-05","科目":"3.銀收","項目":"永豐854","金額":"1700","備註1":"700590619000","備註2":"","編輯":""},{"Key":"3084","日期":"2014-03-05","科目":"3.銀收","項目":"永豐854","金額":"31860","備註1":"露天市集","備註2":"","編輯":""},{"Key":"3085","日期":"2014-03-02","科目":"3.銀收","項目":"永豐854","金額":"350","備註1":"012168099537","備註2":"","編輯":""},{"Key":"3126","日期":"2014-03-23","科目":"3.銀收","項目":"郵政劃撥","金額":"2600","備註1":"26762810000074","備註2":"結餘49713","編輯":""},{"Key":"3103","日期":"2014-03-18","科目":"3.銀收","項目":"郵政劃撥","金額":"3500","備註1":"05948910000074","備註2":"結餘47113","編輯":""},{"Key":"3000","日期":"2014-03-06","科目":"3.銀收","項目":"郵政劃撥","金額":"450","備註1":"代收貨價","備註2":"結餘43613","編輯":""},{"Key":"3006","日期":"2014-03-18","科目":"5.支出","項目":"交通費","金額":"7346","備註1":"中信卡","備註2":"加油費","編輯":""},{"Key":"2835","日期":"2014-03-01","科目":"5.支出","項目":"交通費","金額":"136","備註1":"加油費","備註2":"","編輯":""},{"Key":"2864","日期":"2014-03-04","科目":"5.支出","項目":"交際費-耳機","金額":"4000","備註1":"活動贊助","備註2":"世新大學新弦獎","編輯":""},{"Key":"2998","日期":"2014-03-18","科目":"5.支出","項目":"保險費","金額":"6240","備註1":"大眾卡","備註2":"國泰產險103年度火險","編輯":""},{"Key":"3100","日期":"2014-03-27","科目":"5.支出","項目":"健保-CBHD","金額":"5353","備註1":"加煒","備註2":"103-2","編輯":""},{"Key":"3104","日期":"2014-03-26","科目":"5.支出","項目":"健保-CBHD","金額":"5353","備註1":"加煒","備註2":"103-2","編輯":""},{"Key":"3101","日期":"2014-03-27","科目":"5.支出","項目":"健保-耳機","金額":"9796","備註1":"聲陞","備註2":"103-2","編輯":""},{"Key":"3105","日期":"2014-03-26","科目":"5.支出","項目":"健保-耳機","金額":"9796","備註1":"聲陞","備註2":"103-2","編輯":""},{"Key":"3092","日期":"2014-03-25","科目":"5.支出","項目":"勞保-CBHD","金額":"6940","備註1":"加煒","備註2":"103-2","編輯":""},{"Key":"3098","日期":"2014-03-27","科目":"5.支出","項目":"勞保-耳機","金額":"13784","備註1":"聲陞","備註2":"103-2","編輯":""},{"Key":"3106","日期":"2014-03-26","科目":"5.支出","項目":"勞保-耳機","金額":"13784","備註1":"聲陞","備註2":"103-2","編輯":""},{"Key":"3057","日期":"2014-03-24","科目":"5.支出","項目":"勞退提撥-CBHD","金額":"2970","備註1":"加煒","備註2":"103-2","編輯":""},{"Key":"3099","日期":"2014-03-27","科目":"5.支出","項目":"勞退提撥-耳機","金額":"7092","備註1":"聲陞","備註2":"103-2","編輯":""},{"Key":"3107","日期":"2014-03-26","科目":"5.支出","項目":"勞退提撥-耳機","金額":"7092","備註1":"聲陞","備註2":"103-2","編輯":""},{"Key":"3005","日期":"2014-03-18","科目":"5.支出","項目":"員工福利","金額":"6587","備註1":"國泰卡","備註2":"春酒","編輯":""},{"Key":"2964","日期":"2014-03-14","科目":"5.支出","項目":"員工福利","金額":"69","備註1":"全家","備註2":"下午茶","編輯":""},{"Key":"2950","日期":"2014-03-12","科目":"5.支出","項目":"員工福利","金額":"120","備註1":"7-11","備註2":"下午茶","編輯":""},{"Key":"2889","日期":"2014-03-07","科目":"5.支出","項目":"員工福利","金額":"145","備註1":"下午零食","備註2":"","編輯":""},{"Key":"2902","日期":"2014-03-10","科目":"5.支出","項目":"宣傳費","金額":"11347","備註1":"AE卡","備註2":"facebook宣傳費","編輯":""},{"Key":"2903","日期":"2014-03-10","科目":"5.支出","項目":"宣傳費","金額":"40464","備註1":"AE卡","備註2":"SCOOTAIRTOTYKYOfor8","編輯":""},{"Key":"2899","日期":"2014-03-10","科目":"5.支出","項目":"差旅費","金額":"5288","備註1":"AE卡","備註2":"國泰人壽平安保險","編輯":""},{"Key":"2900","日期":"2014-03-10","科目":"5.支出","項目":"差旅費","金額":"25565","備註1":"AE卡","備註2":"FOXRENTCAR","編輯":""},{"Key":"2901","日期":"2014-03-10","科目":"5.支出","項目":"差旅費","金額":"10409","備註1":"AE卡","備註2":"加州消費","編輯":""},{"Key":"2993","日期":"2014-03-18","科目":"5.支出","項目":"手續費-CBHD","金額":"6000","備註1":"會計規費","備註2":"1031～2","編輯":""},{"Key":"2992","日期":"2014-03-18","科目":"5.支出","項目":"手續費-耳機","金額":"6000","備註1":"會計規費","備註2":"1031～2","編輯":""},{"Key":"2882","日期":"2014-03-06","科目":"5.支出","項目":"手續費-耳機","金額":"130","備註1":"郵局","備註2":"3件","編輯":""},{"Key":"2883","日期":"2014-03-06","科目":"5.支出","項目":"手續費-耳機","金額":"55","備註1":"全家","備註2":"Y拍","編輯":""},{"Key":"2885","日期":"2014-03-06","科目":"5.支出","項目":"手續費-耳機","金額":"100","備註1":"富邦銀行","備註2":"質押設定手續費","編輯":""},{"Key":"3131","日期":"2014-03-28","科目":"5.支出","項目":"文具","金額":"844","備註1":"光南","備註2":"名片夾資料夾","編輯":""},{"Key":"3133","日期":"2014-03-28","科目":"5.支出","項目":"文具","金額":"299","備註1":"光南","備註2":"掛鉤","編輯":""},{"Key":"3120","日期":"2014-03-27","科目":"5.支出","項目":"文具","金額":"98","備註1":"光南","備註2":"綁線帶白膠","編輯":""},{"Key":"3045","日期":"2014-03-22","科目":"5.支出","項目":"文具","金額":"228","備註1":"成坪","備註2":"包裝袋","編輯":""},{"Key":"2958","日期":"2014-03-13","科目":"5.支出","項目":"文具","金額":"12","備註1":"光南","備註2":"文件","編輯":""},{"Key":"2932","日期":"2014-03-10","科目":"5.支出","項目":"文具","金額":"579","備註1":"光南","備註2":"SD卡","編輯":""},{"Key":"2865","日期":"2014-03-04","科目":"5.支出","項目":"文具","金額":"81","備註1":"光南","備註2":"","編輯":""},{"Key":"2995","日期":"2014-03-18","科目":"5.支出","項目":"服務-耳機","金額":"541","備註1":"大眾卡","備註2":"露天服務費","編輯":""},{"Key":"2996","日期":"2014-03-18","科目":"5.支出","項目":"服務-耳機","金額":"1004","備註1":"大眾卡","備註2":"雅虎服務費","編輯":""},{"Key":"2997","日期":"2014-03-18","科目":"5.支出","項目":"服務-耳機","金額":"462","備註1":"大眾卡","備註2":"Google服務費","編輯":""},{"Key":"2984","日期":"2014-03-17","科目":"5.支出","項目":"服務-耳機","金額":"2070","備註1":"LZ退費","備註2":"林瑋翔","編輯":""},{"Key":"2985","日期":"2014-03-17","科目":"5.支出","項目":"服務-耳機","金額":"1800","備註1":"LZ退費","備註2":"黃健銘","編輯":""},{"Key":"3115","日期":"2014-03-26","科目":"5.支出","項目":"清潔用品","金額":"450","備註1":"全家","備註2":"垃圾袋","編輯":""},{"Key":"3071","日期":"2014-03-24","科目":"5.支出","項目":"清潔用品","金額":"70","備註1":"","備註2":"酒精棉片","編輯":""},{"Key":"3004","日期":"2014-03-18","科目":"5.支出","項目":"清潔用品","金額":"999","備註1":"國泰卡","備註2":"PCHOME衛生紙","編輯":""},{"Key":"2951","日期":"2014-03-12","科目":"5.支出","項目":"清潔用品","金額":"85","備註1":"光南","備註2":"浴廁劑","編輯":""},{"Key":"3132","日期":"2014-03-28","科目":"5.支出","項目":"瓦斯費","金額":"275","備註1":"5KG","備註2":"","編輯":""},{"Key":"2994","日期":"2014-03-18","科目":"5.支出","項目":"租任管理","金額":"1200","備註1":"代繳2代健保費","備註2":"1031～2","編輯":""},{"Key":"2991","日期":"2014-03-18","科目":"5.支出","項目":"稅賦-CBHD","金額":"61292","備註1":"營業稅","備註2":"1031～2","編輯":""},{"Key":"3068","日期":"2014-03-24","科目":"5.支出","項目":"稅賦-耳機","金額":"288","備註1":"DHL","備註2":"CTM","編輯":""},{"Key":"2990","日期":"2014-03-18","科目":"5.支出","項目":"稅賦-耳機","金額":"44265","備註1":"營業稅","備註2":"1031～2","編輯":""},{"Key":"2988","日期":"2014-03-17","科目":"5.支出","項目":"稅賦-耳機","金額":"11","備註1":"335","備註2":"所得稅","編輯":""},{"Key":"2966","日期":"2014-03-14","科目":"5.支出","項目":"稅賦-耳機","金額":"2465","備註1":"UPS","備註2":"UE關稅*2","編輯":""},{"Key":"2946","日期":"2014-03-12","科目":"5.支出","項目":"稅賦-耳機","金額":"8772","備註1":"Fedex","備註2":"LZ","編輯":""},{"Key":"2897","日期":"2014-03-07","科目":"5.支出","項目":"稅賦-耳機","金額":"2046","備註1":"關稅","備註2":"UE","編輯":""},{"Key":"2851","日期":"2014-03-03","科目":"5.支出","項目":"薪資","金額":"33000","備註1":"劉承恩","備註2":"2月","編輯":""},{"Key":"2852","日期":"2014-03-03","科目":"5.支出","項目":"薪資","金額":"33000","備註1":"王承顗","備註2":"2月","編輯":""},{"Key":"2853","日期":"2014-03-03","科目":"5.支出","項目":"薪資","金額":"37722","備註1":"吳韻瑤","備註2":"2月","編輯":""},{"Key":"2854","日期":"2014-03-03","科目":"5.支出","項目":"薪資","金額":"19419","備註1":"張凱勝","備註2":"2月","編輯":""},{"Key":"2855","日期":"2014-03-03","科目":"5.支出","項目":"薪資","金額":"40000","備註1":"賴加陞","備註2":"2月","編輯":""},{"Key":"2856","日期":"2014-03-03","科目":"5.支出","項目":"薪資","金額":"40000","備註1":"江雨蓉","備註2":"2月","編輯":""},{"Key":"2857","日期":"2014-03-03","科目":"5.支出","項目":"薪資","金額":"22776","備註1":"潘彥成","備註2":"2月","編輯":""},{"Key":"2858","日期":"2014-03-03","科目":"5.支出","項目":"薪資","金額":"33000","備註1":"賴柏宏","備註2":"2月","編輯":""},{"Key":"3112","日期":"2014-03-26","科目":"5.支出","項目":"貨款-耳機","金額":"2250","備註1":"勝眾","備註2":"維修費","編輯":""},{"Key":"3113","日期":"2014-03-26","科目":"5.支出","項目":"貨款-耳機","金額":"2100","備註1":"博士","備註2":"耳膜3副","編輯":""},{"Key":"3096","日期":"2014-03-25","科目":"5.支出","項目":"貨款-耳機","金額":"1100","備註1":"思維","備註2":"耳機補款","編輯":""},{"Key":"3074","日期":"2014-03-24","科目":"5.支出","項目":"貨款-耳機","金額":"10750","備註1":"吳坤霖","備註2":"退返款","編輯":""},{"Key":"3036","日期":"2014-03-21","科目":"5.支出","項目":"貨款-耳機","金額":"18250","備註1":"CTM","備註2":"原22200USD585*30.65+320進貨單號:1399,1326","編輯":""},{"Key":"3020","日期":"2014-03-19","科目":"5.支出","項目":"貨款-耳機","金額":"74956","備註1":"SINGAPORED&A","備註2":"USD2481.9*30.44+320","編輯":""},{"Key":"3022","日期":"2014-03-19","科目":"5.支出","項目":"貨款-耳機","金額":"183336","備註1":"Rooth","備註2":"37058*4.93+320+320進貨單號:1511,1347,1323,1300,1183","編輯":""},{"Key":"3023","日期":"2014-03-19","科目":"5.支出","項目":"貨款-耳機","金額":"74956","備註1":"D&A","備註2":"ALO","編輯":""},{"Key":"3029","日期":"2014-03-19","科目":"5.支出","項目":"貨款-耳機","金額":"700","備註1":"博士聽覺","備註2":"耳膜＊1","編輯":""},{"Key":"3016","日期":"2014-03-18","科目":"5.支出","項目":"貨款-耳機","金額":"1800","備註1":"LZ退費","備註2":"林廷洋","編輯":""},{"Key":"3018","日期":"2014-03-18","科目":"5.支出","項目":"貨款-耳機","金額":"131450","備註1":"RSA","備註2":"USD2971*30.37+1324*30.65+320+320","編輯":""},{"Key":"3007","日期":"2014-03-17","科目":"5.支出","項目":"貨款-耳機","金額":"90490","備註1":"HIFIMAN","備註2":"USD2971*30.35+320","編輯":""},{"Key":"2947","日期":"2014-03-12","科目":"5.支出","項目":"貨款-耳機","金額":"5500","備註1":"思維","備註2":"UMPRO30維修","編輯":""},{"Key":"2940","日期":"2014-03-11","科目":"5.支出","項目":"貨款-耳機","金額":"2800","備註1":"博士聽覺","備註2":"4只","編輯":""},{"Key":"2917","日期":"2014-03-10","科目":"5.支出","項目":"貨款-耳機","金額":"200195","備註1":"Sony","備註2":"原380919-13230補PHA1共計367689進貨單號:1398,1406,1396,1389,1384,1369,1355,1364,1365,1366","編輯":""},{"Key":"2967","日期":"2014-03-10","科目":"5.支出","項目":"貨款-耳機","金額":"17211","備註1":"CustomArt","備註2":"原14400ERU399.88*42.24+320進貨單號:1325,1185","編輯":""},{"Key":"2603","日期":"2014-03-03","科目":"5.支出","項目":"貨款-耳機","金額":"96862","備註1":"AKG","備註2":"進貨單號:1239,1208,1164,1130","編輯":""},{"Key":"3001","日期":"2014-03-18","科目":"5.支出","項目":"貨款-餐飲","金額":"6344","備註1":"國泰卡","備註2":"好市多","編輯":""},{"Key":"2836","日期":"2014-03-01","科目":"5.支出","項目":"貨款-餐飲","金額":"469","備註1":"全聯","備註2":"牛奶","編輯":""},{"Key":"3149","日期":"2014-03-31","科目":"5.支出","項目":"運費-耳機","金額":"150","備註1":"郵局","備註2":"14件","編輯":""},{"Key":"3150","日期":"2014-03-31","科目":"5.支出","項目":"運費-耳機","金額":"110","備註1":"7-11","備註2":"2件","編輯":""},{"Key":"3121","日期":"2014-03-27","科目":"5.支出","項目":"運費-耳機","金額":"30","備註1":"郵局","備註2":"1件","編輯":""},{"Key":"3114","日期":"2014-03-26","科目":"5.支出","項目":"運費-耳機","金額":"500","備註1":"7-11","備註2":"iCash儲值","編輯":""},{"Key":"3069","日期":"2014-03-24","科目":"5.支出","項目":"運費-耳機","金額":"165","備註1":"7-11","備註2":"露天交貨便3件","編輯":""},{"Key":"3070","日期":"2014-03-24","科目":"5.支出","項目":"運費-耳機","金額":"450","備註1":"郵局","備註2":"5件","編輯":""},{"Key":"3035","日期":"2014-03-20","科目":"5.支出","項目":"運費-耳機","金額":"610","備註1":"郵局","備註2":"2件","編輯":""},{"Key":"3028","日期":"2014-03-19","科目":"5.支出","項目":"運費-耳機","金額":"185","備註1":"郵局","備註2":"3件","編輯":""},{"Key":"3013","日期":"2014-03-18","科目":"5.支出","項目":"運費-耳機","金額":"100","備註1":"郵局","備註2":"3件","編輯":""},{"Key":"3014","日期":"2014-03-18","科目":"5.支出","項目":"運費-耳機","金額":"55","備註1":"全家","備註2":"YAHOO拍賣","編輯":""},{"Key":"2986","日期":"2014-03-17","科目":"5.支出","項目":"運費-耳機","金額":"500","備註1":"7-11","備註2":"加值","編輯":""},{"Key":"2987","日期":"2014-03-17","科目":"5.支出","項目":"運費-耳機","金額":"510","備註1":"郵局","備註2":"4件","編輯":""},{"Key":"2965","日期":"2014-03-14","科目":"5.支出","項目":"運費-耳機","金額":"110","備註1":"7-11","備註2":"露天交貨便","編輯":""},{"Key":"2957","日期":"2014-03-13","科目":"5.支出","項目":"運費-耳機","金額":"200","備註1":"郵局","備註2":"4件","編輯":""},{"Key":"2948","日期":"2014-03-12","科目":"5.支出","項目":"運費-耳機","金額":"100","備註1":"7-11","備註2":"便利袋","編輯":""},{"Key":"2949","日期":"2014-03-12","科目":"5.支出","項目":"運費-耳機","金額":"55","備註1":"7-11","備註2":"露天交貨便","編輯":""},{"Key":"2938","日期":"2014-03-11","科目":"5.支出","項目":"運費-耳機","金額":"292","備註1":"郵局","備註2":"8件","編輯":""},{"Key":"2931","日期":"2014-03-10","科目":"5.支出","項目":"運費-耳機","金額":"3027","備註1":"郵局","備註2":"7件","編輯":""},{"Key":"2933","日期":"2014-03-10","科目":"5.支出","項目":"運費-耳機","金額":"938","備註1":"快遞","備註2":"耳機盒","編輯":""},{"Key":"2875","日期":"2014-03-05","科目":"5.支出","項目":"運費-耳機","金額":"160","備註1":"郵局","備註2":"2件","編輯":""},{"Key":"2866","日期":"2014-03-04","科目":"5.支出","項目":"運費-耳機","金額":"200","備註1":"郵局","備註2":"3件","編輯":""},{"Key":"2850","日期":"2014-03-03","科目":"5.支出","項目":"運費-耳機","金額":"140","備註1":"郵局","備註2":"4件","編輯":""},{"Key":"2837","日期":"2014-03-01","科目":"5.支出","項目":"運費-耳機","金額":"500","備註1":"7-11","備註2":"iCash","編輯":""},{"Key":"2999","日期":"2014-03-18","科目":"5.支出","項目":"雜費","金額":"6794","備註1":"大眾卡","備註2":"PCHOME","編輯":""},{"Key":"3002","日期":"2014-03-18","科目":"5.支出","項目":"雜費","金額":"56421","備註1":"國泰卡","備註2":"承顗蘋果電腦","編輯":""},{"Key":"3003","日期":"2014-03-18","科目":"5.支出","項目":"雜費","金額":"270","備註1":"國泰卡","備註2":"蘋果線上服務","編輯":""},{"Key":"2841","日期":"2014-03-02","科目":"5.支出","項目":"雜費","金額":"360","備註1":"水源市場","備註2":"拜拜水果","編輯":""},{"Key":"3055","日期":"2014-03-24","科目":"5.支出","項目":"電信費","金額":"1522","備註1":"23653115","備註2":"103-2","編輯":""},{"Key":"3056","日期":"2014-03-24","科目":"5.支出","項目":"電信費","金額":"770","備註1":"23651207","備註2":"103-2","編輯":""},{"Key":"2898","日期":"2014-03-07","科目":"5.支出","項目":"電信費","金額":"863","備註1":"0988538527","備註2":"2013-1","編輯":""},{"Key":"3147","日期":"2014-03-31","科目":"5.支出","項目":"餐費","金額":"364","備註1":"午餐","備註2":"3人","編輯":""},{"Key":"3148","日期":"2014-03-31","科目":"5.支出","項目":"餐費","金額":"388","備註1":"晚餐","備註2":"3人","編輯":""},{"Key":"3142","日期":"2014-03-30","科目":"5.支出","項目":"餐費","金額":"685","備註1":"午餐","備註2":"5人","編輯":""},{"Key":"3143","日期":"2014-03-30","科目":"5.支出","項目":"餐費","金額":"589","備註1":"晚餐","備註2":"4人","編輯":""},{"Key":"3137","日期":"2014-03-29","科目":"5.支出","項目":"餐費","金額":"375","備註1":"午餐","備註2":"5人","編輯":""},{"Key":"3138","日期":"2014-03-29","科目":"5.支出","項目":"餐費","金額":"1472","備註1":"晚餐","備註2":"8人","編輯":""},{"Key":"3129","日期":"2014-03-28","科目":"5.支出","項目":"餐費","金額":"305","備註1":"午餐","備註2":"3人","編輯":""},{"Key":"3130","日期":"2014-03-28","科目":"5.支出","項目":"餐費","金額":"650","備註1":"晚餐","備註2":"5人","編輯":""},{"Key":"3118","日期":"2014-03-27","科目":"5.支出","項目":"餐費","金額":"390","備註1":"午餐","備註2":"4人","編輯":""},{"Key":"3119","日期":"2014-03-27","科目":"5.支出","項目":"餐費","金額":"270","備註1":"晚餐","備註2":"3人","編輯":""},{"Key":"3110","日期":"2014-03-26","科目":"5.支出","項目":"餐費","金額":"330","備註1":"中餐","備註2":"3人","編輯":""},{"Key":"3111","日期":"2014-03-26","科目":"5.支出","項目":"餐費","金額":"360","備註1":"晚餐","備註2":"3人","編輯":""},{"Key":"3097","日期":"2014-03-25","科目":"5.支出","項目":"餐費","金額":"190","備註1":"午晚餐","備註2":"1人","編輯":""},{"Key":"3067","日期":"2014-03-24","科目":"5.支出","項目":"餐費","金額":"255","備註1":"中餐","備註2":"3人","編輯":""},{"Key":"3072","日期":"2014-03-24","科目":"5.支出","項目":"餐費","金額":"400","備註1":"晚餐","備註2":"4人","編輯":""},{"Key":"3051","日期":"2014-03-23","科目":"5.支出","項目":"餐費","金額":"440","備註1":"午餐","備註2":"4人","編輯":""},{"Key":"3046","日期":"2014-03-22","科目":"5.支出","項目":"餐費","金額":"340","備註1":"午餐","備註2":"4人","編輯":""},{"Key":"3047","日期":"2014-03-22","科目":"5.支出","項目":"餐費","金額":"440","備註1":"晚餐","備註2":"5人","編輯":""},{"Key":"3039","日期":"2014-03-21","科目":"5.支出","項目":"餐費","金額":"302","備註1":"中餐","備註2":"3人","編輯":""},{"Key":"3040","日期":"2014-03-21","科目":"5.支出","項目":"餐費","金額":"553","備註1":"晚餐","備註2":"4人","編輯":""},{"Key":"3041","日期":"2014-03-21","科目":"5.支出","項目":"餐費","金額":"1715","備註1":"郵局","備註2":"6件","編輯":""},{"Key":"3033","日期":"2014-03-20","科目":"5.支出","項目":"餐費","金額":"134","備註1":"午餐","備註2":"2人","編輯":""},{"Key":"3034","日期":"2014-03-20","科目":"5.支出","項目":"餐費","金額":"390","備註1":"晚餐","備註2":"3人","編輯":""},{"Key":"3026","日期":"2014-03-19","科目":"5.支出","項目":"餐費","金額":"450","備註1":"中餐","備註2":"4人","編輯":""},{"Key":"3027","日期":"2014-03-19","科目":"5.支出","項目":"餐費","金額":"380","備註1":"晚餐","備註2":"5人","編輯":""},{"Key":"3011","日期":"2014-03-18","科目":"5.支出","項目":"餐費","金額":"345","備註1":"午餐","備註2":"3人","編輯":""},{"Key":"3012","日期":"2014-03-18","科目":"5.支出","項目":"餐費","金額":"300","備註1":"晚餐","備註2":"4人","編輯":""},{"Key":"3015","日期":"2014-03-18","科目":"5.支出","項目":"餐費","金額":"300","備註1":"午餐(3/17)","備註2":"3人","編輯":""},{"Key":"2983","日期":"2014-03-17","科目":"5.支出","項目":"餐費","金額":"345","備註1":"晚餐","備註2":"3人","編輯":""},{"Key":"2977","日期":"2014-03-16","科目":"5.支出","項目":"餐費","金額":"520","備註1":"中餐","備註2":"4人","編輯":""},{"Key":"2978","日期":"2014-03-16","科目":"5.支出","項目":"餐費","金額":"210","備註1":"晚餐","備註2":"3人","編輯":""},{"Key":"2971","日期":"2014-03-15","科目":"5.支出","項目":"餐費","金額":"267","備註1":"午餐","備註2":"3人","編輯":""},{"Key":"2972","日期":"2014-03-15","科目":"5.支出","項目":"餐費","金額":"1003","備註1":"晚餐","備註2":"6人","編輯":""},{"Key":"2962","日期":"2014-03-14","科目":"5.支出","項目":"餐費","金額":"240","備註1":"午餐","備註2":"3人","編輯":""},{"Key":"2963","日期":"2014-03-14","科目":"5.支出","項目":"餐費","金額":"500","備註1":"晚餐","備註2":"3人","編輯":""},{"Key":"2955","日期":"2014-03-13","科目":"5.支出","項目":"餐費","金額":"235","備註1":"午餐","備註2":"3人","編輯":""},{"Key":"2956","日期":"2014-03-13","科目":"5.支出","項目":"餐費","金額":"295","備註1":"晚餐","備註2":"3人","編輯":""},{"Key":"2944","日期":"2014-03-12","科目":"5.支出","項目":"餐費","金額":"388","備註1":"午餐","備註2":"4人","編輯":""},{"Key":"2945","日期":"2014-03-12","科目":"5.支出","項目":"餐費","金額":"595","備註1":"晚餐","備註2":"4人","編輯":""},{"Key":"2936","日期":"2014-03-11","科目":"5.支出","項目":"餐費","金額":"410","備註1":"午餐","備註2":"3人","編輯":""},{"Key":"2937","日期":"2014-03-11","科目":"5.支出","項目":"餐費","金額":"270","備註1":"晚餐","備註2":"3人","編輯":""},{"Key":"2939","日期":"2014-03-11","科目":"5.支出","項目":"餐費","金額":"60","備註1":"全家","備註2":"YAHOO交貨便","編輯":""},{"Key":"2929","日期":"2014-03-10","科目":"5.支出","項目":"餐費","金額":"458","備註1":"午餐","備註2":"4人","編輯":""},{"Key":"2930","日期":"2014-03-10","科目":"5.支出","項目":"餐費","金額":"335","備註1":"晚餐","備註2":"3人","編輯":""},{"Key":"2925","日期":"2014-03-09","科目":"5.支出","項目":"餐費","金額":"375","備註1":"午餐","備註2":"4人","編輯":""},{"Key":"2926","日期":"2014-03-09","科目":"5.支出","項目":"餐費","金額":"683","備註1":"晚餐","備註2":"5人","編輯":""},{"Key":"2895","日期":"2014-03-08","科目":"5.支出","項目":"餐費","金額":"475","備註1":"午餐","備註2":"4人","編輯":""},{"Key":"2896","日期":"2014-03-08","科目":"5.支出","項目":"餐費","金額":"2288","備註1":"晚餐","備註2":"7人","編輯":""},{"Key":"2888","日期":"2014-03-07","科目":"5.支出","項目":"餐費","金額":"85","備註1":"郵局","備註2":"4件","編輯":""},{"Key":"2890","日期":"2014-03-07","科目":"5.支出","項目":"餐費","金額":"390","備註1":"晚餐","備註2":"4人","編輯":""},{"Key":"2891","日期":"2014-03-07","科目":"5.支出","項目":"餐費","金額":"367","備註1":"午餐","備註2":"4人","編輯":""},{"Key":"2880","日期":"2014-03-06","科目":"5.支出","項目":"餐費","金額":"300","備註1":"午餐","備註2":"3人","編輯":""},{"Key":"2881","日期":"2014-03-06","科目":"5.支出","項目":"餐費","金額":"83","備註1":"晚餐","備註2":"3人","編輯":""},{"Key":"2873","日期":"2014-03-05","科目":"5.支出","項目":"餐費","金額":"305","備註1":"午餐","備註2":"3天","編輯":""},{"Key":"2874","日期":"2014-03-05","科目":"5.支出","項目":"餐費","金額":"430","備註1":"晚餐","備註2":"5人","編輯":""},{"Key":"2863","日期":"2014-03-04","科目":"5.支出","項目":"餐費","金額":"750","備註1":"午餐","備註2":"5人","編輯":""},{"Key":"2848","日期":"2014-03-03","科目":"5.支出","項目":"餐費","金額":"460","備註1":"中餐","備註2":"3人","編輯":""},{"Key":"2849","日期":"2014-03-03","科目":"5.支出","項目":"餐費","金額":"250","備註1":"晚餐","備註2":"3人","編輯":""},{"Key":"2842","日期":"2014-03-02","科目":"5.支出","項目":"餐費","金額":"255","備註1":"午餐","備註2":"3人","編輯":""},{"Key":"2843","日期":"2014-03-02","科目":"5.支出","項目":"餐費","金額":"437","備註1":"晚餐","備註2":"4人","編輯":""},{"Key":"2833","日期":"2014-03-01","科目":"5.支出","項目":"餐費","金額":"465","備註1":"午餐","備註2":"6人","編輯":""},{"Key":"2834","日期":"2014-03-01","科目":"5.支出","項目":"餐費","金額":"550","備註1":"晚餐","備註2":"5人","編輯":""},{"Key":"3124","日期":"2014-03-28","科目":"5.現支","項目":"貨款-耳機","金額":"62300","備註1":"久東","備註2":"進貨單號:1551","編輯":""},{"Key":"3122","日期":"2014-03-27","科目":"5.現支","項目":"貨款-耳機","金額":"23212","備註1":"成員企業","備註2":"進貨單號:1558","編輯":""},{"Key":"3050","日期":"2014-03-24","科目":"5.現支","項目":"貨款-耳機","金額":"160200","備註1":"久東","備註2":"進貨單號:1529","編輯":""},{"Key":"3019","日期":"2014-03-19","科目":"5.現支","項目":"貨款-耳機","金額":"36700","備註1":"久東","備註2":"進貨單號:1502,1447","編輯":""},{"Key":"2921","日期":"2014-03-10","科目":"5.現支","項目":"貨款-耳機","金額":"64230","備註1":"UE","備註2":"進貨單號:1327,1301","編輯":""},{"Key":"2859","日期":"2014-03-04","科目":"5.現支","項目":"貨款-耳機","金額":"10660","備註1":"成員企業","備註2":"進貨單號:1382","編輯":""},{"Key":"3123","日期":"2014-03-28","科目":"6.銀支","項目":"貨款-耳機","金額":"10420","備註1":"黑曜石","備註2":"進貨單號:1550","編輯":""},{"Key":"3125","日期":"2014-03-28","科目":"6.銀支","項目":"貨款-耳機","金額":"34737","備註1":"聚勝","備註2":"進貨單號:1542","編輯":""},{"Key":"2979","日期":"2014-03-17","科目":"6.銀支","項目":"貨款-耳機","金額":"1880","備註1":"黑曜石","備註2":"進貨單號:1467","編輯":""},{"Key":"2980","日期":"2014-03-17","科目":"6.銀支","項目":"貨款-耳機","金額":"8374","備註1":"聚勝","備註2":"進貨單號:1483","編輯":""},{"Key":"2918","日期":"2014-03-10","科目":"6.銀支","項目":"貨款-耳機","金額":"69783","備註1":"Sony","備註2":"進貨單號:1339,1344,1338,1318","編輯":""},{"Key":"2919","日期":"2014-03-10","科目":"6.銀支","項目":"貨款-耳機","金額":"97713","備註1":"Sony","備註2":"進貨單號:1311,1302,1308,1297","編輯":""},{"Key":"2867","日期":"2014-03-05","科目":"6.銀支","項目":"貨款-耳機","金額":"25252","備註1":"電光火石","備註2":"進貨單號:1370,1269","編輯":""},{"Key":"2868","日期":"2014-03-05","科目":"6.銀支","項目":"貨款-耳機","金額":"222700","備註1":"久東","備註2":"進貨單號:1417","編輯":""},{"Key":"2869","日期":"2014-03-05","科目":"6.銀支","項目":"貨款-耳機","金額":"19820","備註1":"MyEar","備註2":"進貨單號:1401,1378,1336","編輯":""},{"Key":"2876","日期":"2014-03-05","科目":"6.銀支","項目":"貨款-耳機","金額":"6270","備註1":"MyEar","備註2":"進貨單號:1439","編輯":""},{"Key":"2844","日期":"2014-03-03","科目":"6.銀支","項目":"貨款-耳機","金額":"23322","備註1":"聚勝","備註2":"進貨單號:1414","編輯":""},{"Key":"2704","日期":"2014-03-31","科目":"8.票支","項目":"貨款-耳機","金額":"74480","備註1":"永聖","備註2":"451","編輯":""},{"Key":"2877","日期":"2014-03-31","科目":"8.票支","項目":"貨款-耳機","金額":"115038","備註1":"富銘","備註2":"470","編輯":""},{"Key":"2904","日期":"2014-03-31","科目":"8.票支","項目":"貨款-耳機","金額":"29450","備註1":"CHORD","備註2":"471","編輯":""},{"Key":"2905","日期":"2014-03-31","科目":"8.票支","項目":"貨款-耳機","金額":"35020","備註1":"迎家音響","備註2":"472","編輯":""},{"Key":"2907","日期":"2014-03-31","科目":"8.票支","項目":"貨款-耳機","金額":"30750","備註1":"水木清華","備註2":"474","編輯":""},{"Key":"2908","日期":"2014-03-31","科目":"8.票支","項目":"貨款-耳機","金額":"52952","備註1":"鍵寧","備註2":"475","編輯":""},{"Key":"2909","日期":"2014-03-31","科目":"8.票支","項目":"貨款-耳機","金額":"7000","備註1":"福群","備註2":"476","編輯":""},{"Key":"2911","日期":"2014-03-31","科目":"8.票支","項目":"貨款-耳機","金額":"9972","備註1":"泳銓","備註2":"477","編輯":""},{"Key":"2912","日期":"2014-03-31","科目":"8.票支","項目":"貨款-耳機","金額":"70000","備註1":"百鳴","備註2":"478","編輯":""},{"Key":"2913","日期":"2014-03-31","科目":"8.票支","項目":"貨款-耳機","金額":"42960","備註1":"鈦孚","備註2":"479","編輯":""},{"Key":"2915","日期":"2014-03-31","科目":"8.票支","項目":"貨款-耳機","金額":"584760","備註1":"鼎恆","備註2":"481","編輯":""},{"Key":"3048","日期":"2014-03-31","科目":"8.票支","項目":"貨款-耳機","金額":"20610","備註1":"管迷","備註2":"490","編輯":""},{"Key":"3058","日期":"2014-03-31","科目":"8.票支","項目":"貨款-耳機","金額":"25540","備註1":"皇佳","備註2":"492","編輯":""},{"Key":"3060","日期":"2014-03-31","科目":"8.票支","項目":"貨款-耳機","金額":"167548","備註1":"零壹","備註2":"494","編輯":""},{"Key":"3061","日期":"2014-03-31","科目":"8.票支","項目":"貨款-耳機","金額":"29000","備註1":"世貨","備註2":"495","編輯":""},{"Key":"3062","日期":"2014-03-31","科目":"8.票支","項目":"貨款-耳機","金額":"406875","備註1":"宙宣","備註2":"496","編輯":""},{"Key":"3049","日期":"2014-03-23","科目":"8.票支","項目":"貨款-耳機","金額":"7426","備註1":"DHL快遞","備註2":"491","編輯":""},{"Key":"2914","日期":"2014-03-15","科目":"8.票支","項目":"貨款-耳機","金額":"30250","備註1":"先鋒","備註2":"480","編輯":""},{"Key":"2920","日期":"2014-03-10","科目":"8.票支","項目":"貨款-耳機","金額":"14000","備註1":"金山","備註2":"483","編輯":""}]