[{"Key":"Key","日期":"日期","科目":"科目","項目":"項目","金額":"金額","備註1":"備註1","備註2":"備註2","編輯":"編輯"},{"Key":"5685","日期":"2014-12-31","科目":"1.現收","項目":"中信(V+M+J)","金額":"22450","備註1":"12/31","備註2":"22046","編輯":""},{"Key":"5661","日期":"2014-12-30","科目":"1.現收","項目":"中信(V+M+J)","金額":"3930","備註1":"12/31","備註2":"3859","編輯":""},{"Key":"5646","日期":"2014-12-29","科目":"1.現收","項目":"中信(V+M+J)","金額":"2800","備註1":"12/30","備註2":"2750","編輯":""},{"Key":"5637","日期":"2014-12-28","科目":"1.現收","項目":"中信(V+M+J)","金額":"30460","備註1":"12/29","備註2":"29912","編輯":""},{"Key":"5628","日期":"2014-12-27","科目":"1.現收","項目":"中信(V+M+J)","金額":"19400","備註1":"12/29","備註2":"19051","編輯":""},{"Key":"5619","日期":"2014-12-26","科目":"1.現收","項目":"中信(V+M+J)","金額":"46640","備註1":"12/17","備註2":"45800","編輯":""},{"Key":"5609","日期":"2014-12-25","科目":"1.現收","項目":"中信(V+M+J)","金額":"30670","備註1":"12/26","備註2":"30118","編輯":""},{"Key":"5580","日期":"2014-12-24","科目":"1.現收","項目":"中信(V+M+J)","金額":"1200","備註1":"12/25","備註2":"1178","編輯":""},{"Key":"5559","日期":"2014-12-22","科目":"1.現收","項目":"中信(V+M+J)","金額":"2800","備註1":"12/23","備註2":"2750","編輯":""},{"Key":"5534","日期":"2014-12-21","科目":"1.現收","項目":"中信(V+M+J)","金額":"94360","備註1":"12/22","備註2":"92662","編輯":""},{"Key":"5511","日期":"2014-12-18","科目":"1.現收","項目":"中信(V+M+J)","金額":"12850","備註1":"12/19","備註2":"12619","編輯":""},{"Key":"5497","日期":"2014-12-16","科目":"1.現收","項目":"中信(V+M+J)","金額":"27950","備註1":"12/17","備註2":"27447","編輯":""},{"Key":"5488","日期":"2014-12-15","科目":"1.現收","項目":"中信(V+M+J)","金額":"10200","備註1":"12/16","備註2":"10016","編輯":""},{"Key":"5478","日期":"2014-12-14","科目":"1.現收","項目":"中信(V+M+J)","金額":"6400","備註1":"12/15","備註2":"6285","編輯":""},{"Key":"5460","日期":"2014-12-13","科目":"1.現收","項目":"中信(V+M+J)","金額":"45040","備註1":"12/15","備註2":"44229","編輯":""},{"Key":"5453","日期":"2014-12-12","科目":"1.現收","項目":"中信(V+M+J)","金額":"6450","備註1":"12/15","備註2":"6334","編輯":""},{"Key":"5443","日期":"2014-12-11","科目":"1.現收","項目":"中信(V+M+J)","金額":"4300","備註1":"12/12","備註2":"4223","編輯":""},{"Key":"5437","日期":"2014-12-10","科目":"1.現收","項目":"中信(V+M+J)","金額":"10280","備註1":"12/11","備註2":"10095","編輯":""},{"Key":"5427","日期":"2014-12-09","科目":"1.現收","項目":"中信(V+M+J)","金額":"33250","備註1":"12/10","備註2":"32651","編輯":""},{"Key":"5422","日期":"2014-12-08","科目":"1.現收","項目":"中信(V+M+J)","金額":"5800","備註1":"12/9","備註2":"5696","編輯":""},{"Key":"5403","日期":"2014-12-07","科目":"1.現收","項目":"中信(V+M+J)","金額":"48300","備註1":"12/8","備註2":"47431","編輯":""},{"Key":"5393","日期":"2014-12-06","科目":"1.現收","項目":"中信(V+M+J)","金額":"36150","備註1":"12/8","備註2":"35499","編輯":""},{"Key":"5386","日期":"2014-12-05","科目":"1.現收","項目":"中信(V+M+J)","金額":"17850","備註1":"12/8","備註2":"17529","編輯":""},{"Key":"5378","日期":"2014-12-04","科目":"1.現收","項目":"中信(V+M+J)","金額":"6700","備註1":"12/5","備註2":"6579","編輯":""},{"Key":"5372","日期":"2014-12-03","科目":"1.現收","項目":"中信(V+M+J)","金額":"15700","備註1":"12/4","備註2":"15417","編輯":""},{"Key":"5356","日期":"2014-12-02","科目":"1.現收","項目":"中信(V+M+J)","金額":"17690","備註1":"12/3","備註2":"17372","編輯":""},{"Key":"5345","日期":"2014-12-01","科目":"1.現收","項目":"中信(V+M+J)","金額":"12050","備註1":"12/2","備註2":"11833","編輯":""},{"Key":"5569","日期":"2014-12-23","科目":"1.現收","項目":"中信_分12期","金額":"48000","備註1":"12/24","備註2":"44880","編輯":""},{"Key":"5461","日期":"2014-12-13","科目":"1.現收","項目":"中信_分3期","金額":"4700","備註1":"12/16","備註2":"4606","編輯":""},{"Key":"5444","日期":"2014-12-11","科目":"1.現收","項目":"中信_分3期","金額":"6550","備註1":"12/12","備註2":"6419","編輯":""},{"Key":"5373","日期":"2014-12-03","科目":"1.現收","項目":"中信_分3期","金額":"15500","備註1":"12/4","備註2":"15190","編輯":""},{"Key":"5660","日期":"2014-12-30","科目":"1.現收","項目":"國泰(V+M+J)","金額":"5000","備註1":"1/6","備註2":"4905","編輯":""},{"Key":"5645","日期":"2014-12-29","科目":"1.現收","項目":"國泰(V+M+J)","金額":"13200","備註1":"1/5","備註2":"12949","編輯":""},{"Key":"5636","日期":"2014-12-28","科目":"1.現收","項目":"國泰(V+M+J)","金額":"1300","備註1":"12/31","備註2":"1275","編輯":""},{"Key":"5627","日期":"2014-12-27","科目":"1.現收","項目":"國泰(V+M+J)","金額":"4900","備註1":"12/31","備註2":"4807","編輯":""},{"Key":"5608","日期":"2014-12-25","科目":"1.現收","項目":"國泰(V+M+J)","金額":"51970","備註1":"12/29","備註2":"50983","編輯":""},{"Key":"5579","日期":"2014-12-24","科目":"1.現收","項目":"國泰(V+M+J)","金額":"20250","備註1":"12/27","備註2":"19865","編輯":""},{"Key":"5568","日期":"2014-12-23","科目":"1.現收","項目":"國泰(V+M+J)","金額":"10550","備註1":"12/26","備註2":"10350","編輯":""},{"Key":"5558","日期":"2014-12-22","科目":"1.現收","項目":"國泰(V+M+J)","金額":"3500","備註1":"12/25","備註2":"3433","編輯":""},{"Key":"5533","日期":"2014-12-21","科目":"1.現收","項目":"國泰(V+M+J)","金額":"14950","備註1":"12/24","備註2":"14666","編輯":""},{"Key":"5509","日期":"2014-12-18","科目":"1.現收","項目":"國泰(V+M+J)","金額":"24600","備註1":"12/23","備註2":"24133","編輯":""},{"Key":"5501","日期":"2014-12-17","科目":"1.現收","項目":"國泰(V+M+J)","金額":"2400","備註1":"12/22","備註2":"2354","編輯":""},{"Key":"5496","日期":"2014-12-16","科目":"1.現收","項目":"國泰(V+M+J)","金額":"2700","備註1":"12/19","備註2":"2649","編輯":""},{"Key":"5489","日期":"2014-12-15","科目":"1.現收","項目":"國泰(V+M+J)","金額":"270","備註1":"12/18","備註2":"265","編輯":""},{"Key":"5476","日期":"2014-12-14","科目":"1.現收","項目":"國泰(V+M+J)","金額":"15300","備註1":"12/17","備註2":"15009","編輯":""},{"Key":"5459","日期":"2014-12-13","科目":"1.現收","項目":"國泰(V+M+J)","金額":"8370","備註1":"12/17","備註2":"8211","編輯":""},{"Key":"5452","日期":"2014-12-12","科目":"1.現收","項目":"國泰(V+M+J)","金額":"4500","備註1":"12/17","備註2":"4415","編輯":""},{"Key":"5436","日期":"2014-12-10","科目":"1.現收","項目":"國泰(V+M+J)","金額":"6900","備註1":"12/15","備註2":"6769","編輯":""},{"Key":"5428","日期":"2014-12-09","科目":"1.現收","項目":"國泰(V+M+J)","金額":"2790","備註1":"12/12","備註2":"2737","編輯":""},{"Key":"5402","日期":"2014-12-07","科目":"1.現收","項目":"國泰(V+M+J)","金額":"2800","備註1":"12/10","備註2":"2747","編輯":""},{"Key":"5392","日期":"2014-12-06","科目":"1.現收","項目":"國泰(V+M+J)","金額":"10000","備註1":"12/10","備註2":"9810","編輯":""},{"Key":"5387","日期":"2014-12-05","科目":"1.現收","項目":"國泰(V+M+J)","金額":"18200","備註1":"12/10","備註2":"17854","編輯":""},{"Key":"5371","日期":"2014-12-03","科目":"1.現收","項目":"國泰(V+M+J)","金額":"4550","備註1":"12/8","備註2":"4464","編輯":""},{"Key":"5355","日期":"2014-12-02","科目":"1.現收","項目":"國泰(V+M+J)","金額":"9500","備註1":"12/5","備註2":"9319","編輯":""},{"Key":"5510","日期":"2014-12-18","科目":"1.現收","項目":"國泰_分3期","金額":"5800","備註1":"12/23","備註2":"5669","編輯":""},{"Key":"5477","日期":"2014-12-14","科目":"1.現收","項目":"國泰_分3期","金額":"3500","備註1":"12/17","備註2":"3421","編輯":""},{"Key":"5683","日期":"2014-12-31","科目":"1.現收","項目":"耳機現金","金額":"83934","備註1":"","備註2":"","編輯":""},{"Key":"5659","日期":"2014-12-30","科目":"1.現收","項目":"耳機現金","金額":"106182","備註1":"","備註2":"","編輯":""},{"Key":"5643","日期":"2014-12-29","科目":"1.現收","項目":"耳機現金","金額":"37376","備註1":"","備註2":"","編輯":""},{"Key":"5633","日期":"2014-12-28","科目":"1.現收","項目":"耳機現金","金額":"67720","備註1":"","備註2":"","編輯":""},{"Key":"5626","日期":"2014-12-27","科目":"1.現收","項目":"耳機現金","金額":"89292","備註1":"","備註2":"","編輯":""},{"Key":"5617","日期":"2014-12-26","科目":"1.現收","項目":"耳機現金","金額":"57818","備註1":"","備註2":"","編輯":""},{"Key":"5606","日期":"2014-12-25","科目":"1.現收","項目":"耳機現金","金額":"42149","備註1":"","備註2":"","編輯":""},{"Key":"5577","日期":"2014-12-24","科目":"1.現收","項目":"耳機現金","金額":"54004","備註1":"","備註2":"","編輯":""},{"Key":"5567","日期":"2014-12-23","科目":"1.現收","項目":"耳機現金","金額":"19712","備註1":"","備註2":"","編輯":""},{"Key":"5557","日期":"2014-12-22","科目":"1.現收","項目":"耳機現金","金額":"20036","備註1":"","備註2":"","編輯":""},{"Key":"5531","日期":"2014-12-21","科目":"1.現收","項目":"耳機現金","金額":"31615","備註1":"","備註2":"","編輯":""},{"Key":"5525","日期":"2014-12-20","科目":"1.現收","項目":"耳機現金","金額":"70220","備註1":"","備註2":"","編輯":""},{"Key":"5521","日期":"2014-12-19","科目":"1.現收","項目":"耳機現金","金額":"46760","備註1":"","備註2":"","編輯":""},{"Key":"5508","日期":"2014-12-18","科目":"1.現收","項目":"耳機現金","金額":"27790","備註1":"","備註2":"","編輯":""},{"Key":"5499","日期":"2014-12-17","科目":"1.現收","項目":"耳機現金","金額":"39945","備註1":"","備註2":"","編輯":""},{"Key":"5495","日期":"2014-12-16","科目":"1.現收","項目":"耳機現金","金額":"11615","備註1":"","備註2":"","編輯":""},{"Key":"5487","日期":"2014-12-15","科目":"1.現收","項目":"耳機現金","金額":"60320","備註1":"","備註2":"","編輯":""},{"Key":"5474","日期":"2014-12-14","科目":"1.現收","項目":"耳機現金","金額":"75350","備註1":"","備註2":"","編輯":""},{"Key":"5458","日期":"2014-12-13","科目":"1.現收","項目":"耳機現金","金額":"122700","備註1":"","備註2":"","編輯":""},{"Key":"5450","日期":"2014-12-12","科目":"1.現收","項目":"耳機現金","金額":"55407","備註1":"","備註2":"","編輯":""},{"Key":"5442","日期":"2014-12-11","科目":"1.現收","項目":"耳機現金","金額":"38606","備註1":"","備註2":"","編輯":""},{"Key":"5435","日期":"2014-12-10","科目":"1.現收","項目":"耳機現金","金額":"60865","備註1":"","備註2":"","編輯":""},{"Key":"5425","日期":"2014-12-09","科目":"1.現收","項目":"耳機現金","金額":"38765","備註1":"","備註2":"","編輯":""},{"Key":"5421","日期":"2014-12-08","科目":"1.現收","項目":"耳機現金","金額":"20210","備註1":"","備註2":"","編輯":""},{"Key":"5401","日期":"2014-12-07","科目":"1.現收","項目":"耳機現金","金額":"108060","備註1":"","備註2":"","編輯":""},{"Key":"5390","日期":"2014-12-06","科目":"1.現收","項目":"耳機現金","金額":"63360","備註1":"","備註2":"","編輯":""},{"Key":"5384","日期":"2014-12-05","科目":"1.現收","項目":"耳機現金","金額":"92820","備註1":"","備註2":"","編輯":""},{"Key":"5377","日期":"2014-12-04","科目":"1.現收","項目":"耳機現金","金額":"27260","備註1":"","備註2":"","編輯":""},{"Key":"5369","日期":"2014-12-03","科目":"1.現收","項目":"耳機現金","金額":"48555","備註1":"","備註2":"","編輯":""},{"Key":"5354","日期":"2014-12-02","科目":"1.現收","項目":"耳機現金","金額":"11047","備註1":"","備註2":"","編輯":""},{"Key":"5344","日期":"2014-12-01","科目":"1.現收","項目":"耳機現金","金額":"70823","備註1":"","備註2":"","編輯":""},{"Key":"5644","日期":"2014-12-29","科目":"1.現收","項目":"聯信(V-M-J-銀)","金額":"48000","備註1":"1/7","備註2":"47040","編輯":""},{"Key":"5578","日期":"2014-12-24","科目":"1.現收","項目":"聯信(V-M-J-銀)","金額":"4300","備註1":"12/29","備註2":"4214","編輯":""},{"Key":"5526","日期":"2014-12-20","科目":"1.現收","項目":"聯信(V-M-J-銀)","金額":"20200","備註1":"12/25","備註2":"19796","編輯":""},{"Key":"5522","日期":"2014-12-19","科目":"1.現收","項目":"聯信(V-M-J-銀)","金額":"3200","備註1":"12/25","備註2":"3136","編輯":""},{"Key":"5500","日期":"2014-12-17","科目":"1.現收","項目":"聯信(V-M-J-銀)","金額":"6400","備註1":"12/23","備註2":"6272","編輯":""},{"Key":"5475","日期":"2014-12-14","科目":"1.現收","項目":"聯信(V-M-J-銀)","金額":"10000","備註1":"12/19","備註2":"9800","編輯":""},{"Key":"5426","日期":"2014-12-09","科目":"1.現收","項目":"聯信(V-M-J-銀)","金額":"2200","備註1":"12/15","備註2":"2156","編輯":""},{"Key":"5391","日期":"2014-12-06","科目":"1.現收","項目":"聯信(V-M-J-銀)","金額":"9000","備註1":"12/11","備註2":"8820","編輯":""},{"Key":"5634","日期":"2014-12-28","科目":"1.現收","項目":"聯信_AE","金額":"1000","備註1":"1/7","備註2":"960","編輯":""},{"Key":"5607","日期":"2014-12-25","科目":"1.現收","項目":"聯信_分12期","金額":"26600","備註1":"12/30","備註2":"24738","編輯":""},{"Key":"5684","日期":"2014-12-31","科目":"1.現收","項目":"聯信_分3期","金額":"5400","備註1":"1/8","備註2":"5265","編輯":""},{"Key":"5635","日期":"2014-12-28","科目":"1.現收","項目":"聯信_分3期","金額":"6800","備註1":"1/7","備註2":"6630","編輯":""},{"Key":"5618","日期":"2014-12-26","科目":"1.現收","項目":"聯信_分3期","金額":"8660","備註1":"12/31","備註2":"8444","編輯":""},{"Key":"5532","日期":"2014-12-21","科目":"1.現收","項目":"聯信_分3期","金額":"4320","備註1":"12/26","備註2":"4225","編輯":""},{"Key":"5527","日期":"2014-12-20","科目":"1.現收","項目":"聯信_分3期","金額":"9800","備註1":"12/25","備註2":"9585","編輯":""},{"Key":"5385","日期":"2014-12-05","科目":"1.現收","項目":"聯信_分3期","金額":"3100","備註1":"12/11","備註2":"3032","編輯":""},{"Key":"5370","日期":"2014-12-03","科目":"1.現收","項目":"聯信_分3期","金額":"45000","備註1":"12/9","備註2":"43875","編輯":""},{"Key":"5449","日期":"2014-12-12","科目":"2.票收","項目":"票收","金額":"3130","備註1":"華南西門160120246HD50494561030820","備註2":"永偉7月","編輯":""},{"Key":"5351","日期":"2014-12-01","科目":"2.票收","項目":"票收","金額":"4551","備註1":"華南忠興LD2375715/160350664/1031225","備註2":"盈新2014-9","編輯":""},{"Key":"5670","日期":"2014-12-22","科目":"3.銀收","項目":"富邦408","金額":"36245","備註1":"錢櫃","備註2":"103-10","編輯":""},{"Key":"5671","日期":"2014-12-22","科目":"3.銀收","項目":"富邦408","金額":"52377","備註1":"好樂迪","備註2":"103-10","編輯":""},{"Key":"5673","日期":"2014-12-31","科目":"3.銀收","項目":"永豐854","金額":"17220","備註1":"拍賣","備註2":"露天","編輯":""},{"Key":"5672","日期":"2014-12-30","科目":"3.銀收","項目":"永豐854","金額":"460","備註1":"網拍","備註2":"008201032178","編輯":""},{"Key":"5674","日期":"2014-12-26","科目":"3.銀收","項目":"永豐854","金額":"4050","備註1":"網拍","備註2":"822540189041","編輯":""},{"Key":"5675","日期":"2014-12-21","科目":"3.銀收","項目":"永豐854","金額":"5500","備註1":"網拍","備註2":"822540022611","編輯":""},{"Key":"5676","日期":"2014-12-21","科目":"3.銀收","項目":"永豐854","金額":"4","備註1":"利息","備註2":"","編輯":""},{"Key":"5677","日期":"2014-12-19","科目":"3.銀收","項目":"永豐854","金額":"280","備註1":"網拍","備註2":"700062455252","編輯":""},{"Key":"5678","日期":"2014-12-18","科目":"3.銀收","項目":"永豐854","金額":"2690","備註1":"網拍","備註2":"700120160222","編輯":""},{"Key":"5679","日期":"2014-12-12","科目":"3.銀收","項目":"永豐854","金額":"35230","備註1":"網拍","備註2":"露天","編輯":""},{"Key":"5680","日期":"2014-12-10","科目":"3.銀收","項目":"永豐854","金額":"450","備註1":"網拍","備註2":"803508119272","編輯":""},{"Key":"5681","日期":"2014-12-02","科目":"3.銀收","項目":"永豐854","金額":"530","備註1":"網拍","備註2":"700860431601","編輯":""},{"Key":"5682","日期":"2014-12-01","科目":"3.銀收","項目":"永豐854","金額":"2540","備註1":"網拍","備註2":"006227849466","編輯":""},{"Key":"6585","日期":"2014-12-21","科目":"3.銀收","項目":"郵局900","金額":"40","備註1":"利息","備註2":"","編輯":""},{"Key":"5543","日期":"2014-12-22","科目":"5.支出","項目":"交通費","金額":"1902","備註1":"國泰卡","備註2":"全國加油站","編輯":""},{"Key":"5544","日期":"2014-12-22","科目":"5.支出","項目":"交通費","金額":"14035","備註1":"國泰卡","備註2":"KSS","編輯":""},{"Key":"5545","日期":"2014-12-22","科目":"5.支出","項目":"交通費","金額":"4228","備註1":"中信卡","備註2":"全國加油站","編輯":""},{"Key":"5397","日期":"2014-12-08","科目":"5.支出","項目":"交通費","金額":"1050","備註1":"台新卡","備註2":"加油費","編輯":""},{"Key":"5589","日期":"2014-12-25","科目":"5.支出","項目":"健保-CBHD","金額":"9633","備註1":"加煒","備註2":"103-11","編輯":""},{"Key":"5412","日期":"2014-12-08","科目":"5.支出","項目":"健保-CBHD","金額":"7670","備註1":"加煒","備註2":"103-10","編輯":""},{"Key":"5590","日期":"2014-12-25","科目":"5.支出","項目":"健保-耳機","金額":"13352","備註1":"聲陞","備註2":"103-11","編輯":""},{"Key":"5413","日期":"2014-12-08","科目":"5.支出","項目":"健保-耳機","金額":"12103","備註1":"聲陞","備註2":"103-10","編輯":""},{"Key":"5594","日期":"2014-12-25","科目":"5.支出","項目":"勞保-CBHD","金額":"10797","備註1":"加煒","備註2":"103-11","編輯":""},{"Key":"5410","日期":"2014-12-08","科目":"5.支出","項目":"勞保-CBHD","金額":"9294","備註1":"加煒","備註2":"103-10","編輯":""},{"Key":"5415","日期":"2014-12-08","科目":"5.支出","項目":"勞保-CBHD","金額":"9208","備註1":"聲陞","備註2":"103-10","編輯":""},{"Key":"5593","日期":"2014-12-25","科目":"5.支出","項目":"勞保-耳機","金額":"17472","備註1":"聲陞","備註2":"103-11","編輯":""},{"Key":"5414","日期":"2014-12-08","科目":"5.支出","項目":"勞保-耳機","金額":"16879","備註1":"聲陞","備註2":"103-10","編輯":""},{"Key":"5591","日期":"2014-12-25","科目":"5.支出","項目":"勞退提撥-CBHD","金額":"5614","備註1":"加煒","備註2":"103-11","編輯":""},{"Key":"5411","日期":"2014-12-08","科目":"5.支出","項目":"勞退提撥-CBHD","金額":"4584","備註1":"加煒","備註2":"103-10","編輯":""},{"Key":"5592","日期":"2014-12-25","科目":"5.支出","項目":"勞退提撥-耳機","金額":"9442","備註1":"聲陞","備註2":"103-11","編輯":""},{"Key":"5542","日期":"2014-12-22","科目":"5.支出","項目":"差旅費","金額":"33057","備註1":"國泰卡","備註2":"高鐵機票","編輯":""},{"Key":"5516","日期":"2014-12-11","科目":"5.支出","項目":"差旅費","金額":"99180","備註1":"AE卡","備註2":"日本展覽出差","編輯":""},{"Key":"5665","日期":"2014-12-30","科目":"5.支出","項目":"文具","金額":"240","備註1":"光南","備註2":"整理盒","編輯":""},{"Key":"5652","日期":"2014-12-29","科目":"5.支出","項目":"文具","金額":"420","備註1":"光南","備註2":"整理盒","編輯":""},{"Key":"5632","日期":"2014-12-27","科目":"5.支出","項目":"文具","金額":"72","備註1":"光南","備註2":"佈置","編輯":""},{"Key":"5623","日期":"2014-12-26","科目":"5.支出","項目":"文具","金額":"188","備註1":"光南","備註2":"塑膠盒","編輯":""},{"Key":"5613","日期":"2014-12-25","科目":"5.支出","項目":"文具","金額":"617","備註1":"光南","備註2":"文件夾","編輯":""},{"Key":"5584","日期":"2014-12-24","科目":"5.支出","項目":"文具","金額":"29","備註1":"光南","備註2":"文具","編輯":""},{"Key":"5572","日期":"2014-12-23","科目":"5.支出","項目":"文具","金額":"32","備註1":"光南","備註2":"文具","編輯":""},{"Key":"5573","日期":"2014-12-23","科目":"5.支出","項目":"文具","金額":"45","備註1":"成坪","備註2":"夾鏈袋","編輯":""},{"Key":"5530","日期":"2014-12-20","科目":"5.支出","項目":"文具","金額":"100","備註1":"光南","備註2":"夾鏈袋","編輯":""},{"Key":"5486","日期":"2014-12-15","科目":"5.支出","項目":"文具","金額":"350","備註1":"成坪","備註2":"展示盤","編輯":""},{"Key":"5448","日期":"2014-12-12","科目":"5.支出","項目":"文具","金額":"121","備註1":"光南","備註2":"佈置品","編輯":""},{"Key":"5382","日期":"2014-12-04","科目":"5.支出","項目":"文具","金額":"99","備註1":"光南","備註2":"便利貼","編輯":""},{"Key":"5350","日期":"2014-12-01","科目":"5.支出","項目":"文具","金額":"156","備註1":"光南","備註2":"復寫紙","編輯":""},{"Key":"5622","日期":"2014-12-26","科目":"5.支出","項目":"服務-耳機","金額":"3300","備註1":"退款","備註2":"","編輯":""},{"Key":"5518","日期":"2014-12-11","科目":"5.支出","項目":"服務-耳機","金額":"3904","備註1":"AE卡","備註2":"FACEBOOK","編輯":""},{"Key":"5519","日期":"2014-12-11","科目":"5.支出","項目":"服務-耳機","金額":"220","備註1":"富邦","備註2":"人民幣退匯手續費","編輯":""},{"Key":"5398","日期":"2014-12-08","科目":"5.支出","項目":"服務-耳機","金額":"2540","備註1":"華南卡","備註2":"Yahoo拍賣","編輯":""},{"Key":"5399","日期":"2014-12-08","科目":"5.支出","項目":"服務-耳機","金額":"637","備註1":"華南卡","備註2":"露天拍賣","編輯":""},{"Key":"5400","日期":"2014-12-08","科目":"5.支出","項目":"服務-耳機","金額":"463","備註1":"華南卡","備註2":"Google","編輯":""},{"Key":"5658","日期":"2014-12-30","科目":"5.支出","項目":"水費","金額":"535","備註1":"223","備註2":"103-12","編輯":""},{"Key":"5564","日期":"2014-12-22","科目":"5.支出","項目":"清潔用品","金額":"97","備註1":"全聯","備註2":"廚房紙巾","編輯":""},{"Key":"5565","日期":"2014-12-22","科目":"5.支出","項目":"清潔用品","金額":"680","備註1":"無印良品","備註2":"芳香劑","編輯":""},{"Key":"5457","日期":"2014-12-12","科目":"5.支出","項目":"清潔用品","金額":"180","備註1":"全家","備註2":"垃圾袋","編輯":""},{"Key":"5669","日期":"2014-12-31","科目":"5.支出","項目":"租任管理","金額":"3859","備註1":"中信貸款","備註2":"","編輯":""},{"Key":"5409","日期":"2014-12-08","科目":"5.支出","項目":"稅賦-CBHD","金額":"900","備註1":"燃料稅","備註2":"662JBH","編輯":""},{"Key":"5538","日期":"2014-12-22","科目":"5.支出","項目":"稅賦-耳機","金額":"906","備註1":"國稅","備註2":"罰款","編輯":""},{"Key":"5562","日期":"2014-12-22","科目":"5.支出","項目":"稅賦-耳機","金額":"717","備註1":"關稅","備註2":"RSA","編輯":""},{"Key":"5381","日期":"2014-12-04","科目":"5.支出","項目":"稅賦-耳機","金額":"7675","備註1":"關稅","備註2":"aurisonics","編輯":""},{"Key":"5546","日期":"2014-12-22","科目":"5.支出","項目":"薪資","金額":"14594","備註1":"周昱甫","備註2":"103-11","編輯":""},{"Key":"5547","日期":"2014-12-22","科目":"5.支出","項目":"薪資","金額":"40000","備註1":"賴誌良","備註2":"103-11","編輯":""},{"Key":"5548","日期":"2014-12-22","科目":"5.支出","項目":"薪資","金額":"40000","備註1":"江雨蓉","備註2":"103-11","編輯":""},{"Key":"5549","日期":"2014-12-22","科目":"5.支出","項目":"薪資","金額":"40000","備註1":"王承顗","備註2":"103-11","編輯":""},{"Key":"5550","日期":"2014-12-22","科目":"5.支出","項目":"薪資","金額":"34375","備註1":"劉承恩","備註2":"103-11","編輯":""},{"Key":"5551","日期":"2014-12-22","科目":"5.支出","項目":"薪資","金額":"21878","備註1":"陳明勝","備註2":"103-11","編輯":""},{"Key":"5552","日期":"2014-12-22","科目":"5.支出","項目":"薪資","金額":"30485","備註1":"吳韻瑤","備註2":"103-11","編輯":""},{"Key":"5553","日期":"2014-12-22","科目":"5.支出","項目":"薪資","金額":"3697","備註1":"張凱勝","備註2":"103-11","編輯":""},{"Key":"5554","日期":"2014-12-22","科目":"5.支出","項目":"薪資","金額":"9255","備註1":"潘彥成","備註2":"103-11","編輯":""},{"Key":"5555","日期":"2014-12-22","科目":"5.支出","項目":"薪資","金額":"36325","備註1":"賴柏宏","備註2":"103-11","編輯":""},{"Key":"5666","日期":"2014-12-30","科目":"5.支出","項目":"貨款-CBHD","金額":"120","備註1":"電洋","備註2":"電感","編輯":""},{"Key":"5650","日期":"2014-12-29","科目":"5.支出","項目":"貨款-CBHD","金額":"1200","備註1":"成茂","備註2":"喇叭維修費","編輯":""},{"Key":"5484","日期":"2014-12-15","科目":"5.支出","項目":"貨款-CBHD","金額":"220","備註1":"偉帝","備註2":"CDR","編輯":""},{"Key":"5668","日期":"2014-12-30","科目":"5.支出","項目":"貨款-耳機","金額":"700","備註1":"博士聽覺","備註2":"耳膜1付","編輯":""},{"Key":"5586","日期":"2014-12-25","科目":"5.支出","項目":"貨款-耳機","金額":"246000","備註1":"FITEAR","備註2":"進貨單號:2521,2489,2415,2416,2417","編輯":""},{"Key":"5587","日期":"2014-12-25","科目":"5.支出","項目":"貨款-耳機","金額":"24000","備註1":"久東","備註2":"進貨單號:2789","編輯":""},{"Key":"5588","日期":"2014-12-25","科目":"5.支出","項目":"貨款-耳機","金額":"63376","備註1":"音茶樂","備註2":"USD1982.22*31.8+320","編輯":""},{"Key":"5575","日期":"2014-12-23","科目":"5.支出","項目":"貨款-耳機","金額":"700","備註1":"博士聽覺","備註2":"耳膜1付","編輯":""},{"Key":"5504","日期":"2014-12-17","科目":"5.支出","項目":"貨款-耳機","金額":"700","備註1":"博士聽覺","備註2":"耳膜1付","編輯":""},{"Key":"5493","日期":"2014-12-16","科目":"5.支出","項目":"貨款-耳機","金額":"1400","備註1":"博士聽覺","備註2":"耳膜2付","編輯":""},{"Key":"5507","日期":"2014-12-15","科目":"5.支出","項目":"貨款-耳機","金額":"1040","備註1":"黑貓宅便","備註2":"進貨單號:2730","編輯":""},{"Key":"5517","日期":"2014-12-11","科目":"5.支出","項目":"貨款-耳機","金額":"8386","備註1":"CTM","備註2":"AE卡進貨單號:2382","編輯":""},{"Key":"5432","日期":"2014-12-09","科目":"5.支出","項目":"貨款-耳機","金額":"1400","備註1":"博士聽覺","備註2":"耳膜2付","編輯":""},{"Key":"5408","日期":"2014-12-08","科目":"5.支出","項目":"貨款-耳機","金額":"72177","備註1":"RSA","備註2":"USD2300*31.242+320","編輯":""},{"Key":"5348","日期":"2014-12-01","科目":"5.支出","項目":"貨款-耳機","金額":"6300","備註1":"思維","備註2":"維修費","編輯":""},{"Key":"5563","日期":"2014-12-22","科目":"5.支出","項目":"貨款-餐飲","金額":"282","備註1":"全聯","備註2":"牛奶","編輯":""},{"Key":"5447","日期":"2014-12-12","科目":"5.支出","項目":"貨款-餐飲","金額":"450","備註1":"水源市場","備註2":"糖果","編輯":""},{"Key":"5416","日期":"2014-12-08","科目":"5.支出","項目":"貨款-餐飲","金額":"2890","備註1":"花神","備註2":"咖啡豆","編輯":""},{"Key":"5653","日期":"2014-12-30","科目":"5.支出","項目":"貸款清償","金額":"2750","備註1":"中信貸款","備註2":"","編輯":""},{"Key":"5642","日期":"2014-12-29","科目":"5.支出","項目":"貸款清償","金額":"8553","備註1":"中信貸款","備註2":"","編輯":""},{"Key":"5625","日期":"2014-12-27","科目":"5.支出","項目":"貸款清償","金額":"8695","備註1":"中信貸款","備註2":"","編輯":""},{"Key":"5616","日期":"2014-12-26","科目":"5.支出","項目":"貸款清償","金額":"30118","備註1":"中信貸款","備註2":"","編輯":""},{"Key":"5566","日期":"2014-12-23","科目":"5.支出","項目":"貸款清償","金額":"2750","備註1":"中信貸款","備註2":"","編輯":""},{"Key":"5556","日期":"2014-12-22","科目":"5.支出","項目":"貸款清償","金額":"13923","備註1":"中信貸款","備註2":"","編輯":""},{"Key":"5520","日期":"2014-12-19","科目":"5.支出","項目":"貸款清償","金額":"12619","備註1":"中信貸款","備註2":"","編輯":""},{"Key":"5498","日期":"2014-12-17","科目":"5.支出","項目":"貸款清償","金額":"8553","備註1":"中信貸款","備註2":"","編輯":""},{"Key":"5490","日期":"2014-12-16","科目":"5.支出","項目":"貸款清償","金額":"8553","備註1":"中信貸款","備註2":"","編輯":""},{"Key":"5480","日期":"2014-12-15","科目":"5.支出","項目":"貸款清償","金額":"8553","備註1":"中信貸款","備註2":"","編輯":""},{"Key":"5423","日期":"2014-12-09","科目":"5.支出","項目":"貸款清償","金額":"4286","備註1":"中信貸款","備註2":"","編輯":""},{"Key":"5407","日期":"2014-12-08","科目":"5.支出","項目":"貸款清償","金額":"12204","備註1":"中信貸款","備註2":"","編輯":""},{"Key":"5383","日期":"2014-12-05","科目":"5.支出","項目":"貸款清償","金額":"6579","備註1":"中信貸款","備註2":"","編輯":""},{"Key":"5376","日期":"2014-12-04","科目":"5.支出","項目":"貸款清償","金額":"8553","備註1":"中信貸款","備註2":"","編輯":""},{"Key":"5368","日期":"2014-12-03","科目":"5.支出","項目":"貸款清償","金額":"8553","備註1":"中信貸款","備註2":"","編輯":""},{"Key":"5352","日期":"2014-12-02","科目":"5.支出","項目":"貸款清償","金額":"8553","備註1":"中信貸款","備註2":"","編輯":""},{"Key":"5343","日期":"2014-12-01","科目":"5.支出","項目":"貸款清償","金額":"19700","備註1":"中信貸款","備註2":"","編輯":""},{"Key":"5631","日期":"2014-12-27","科目":"5.支出","項目":"運費-CBHD","金額":"70","備註1":"郵局","備註2":"1件","編輯":""},{"Key":"5583","日期":"2014-12-24","科目":"5.支出","項目":"運費-CBHD","金額":"75","備註1":"大榮","備註2":"HD","編輯":""},{"Key":"5515","日期":"2014-12-18","科目":"5.支出","項目":"運費-CBHD","金額":"30","備註1":"郵局","備註2":"1件","編輯":""},{"Key":"5434","日期":"2014-12-09","科目":"5.支出","項目":"運費-CBHD","金額":"230","備註1":"大榮","備註2":"5件","編輯":""},{"Key":"5667","日期":"2014-12-30","科目":"5.支出","項目":"運費-耳機","金額":"25","備註1":"郵局","備註2":"1件","編輯":""},{"Key":"5651","日期":"2014-12-29","科目":"5.支出","項目":"運費-耳機","金額":"420","備註1":"郵局","備註2":"7件","編輯":""},{"Key":"5612","日期":"2014-12-25","科目":"5.支出","項目":"運費-耳機","金額":"85","備註1":"郵局","備註2":"2件","編輯":""},{"Key":"5614","日期":"2014-12-25","科目":"5.支出","項目":"運費-耳機","金額":"627","備註1":"郵局","備註2":"2件","編輯":""},{"Key":"5574","日期":"2014-12-23","科目":"5.支出","項目":"運費-耳機","金額":"30","備註1":"郵局","備註2":"1件","編輯":""},{"Key":"5514","日期":"2014-12-18","科目":"5.支出","項目":"運費-耳機","金額":"160","備註1":"大榮","備註2":"1件","編輯":""},{"Key":"5505","日期":"2014-12-17","科目":"5.支出","項目":"運費-耳機","金額":"450","備註1":"郵局","備註2":"1件","編輯":""},{"Key":"5506","日期":"2014-12-17","科目":"5.支出","項目":"運費-耳機","金額":"120","備註1":"7-11","備註2":"2件","編輯":""},{"Key":"5494","日期":"2014-12-16","科目":"5.支出","項目":"運費-耳機","金額":"104","備註1":"郵局","備註2":"2件","編輯":""},{"Key":"5483","日期":"2014-12-15","科目":"5.支出","項目":"運費-耳機","金額":"243","備註1":"順豐","備註2":"Hifiman","編輯":""},{"Key":"5485","日期":"2014-12-15","科目":"5.支出","項目":"運費-耳機","金額":"210","備註1":"郵局","備註2":"6件","編輯":""},{"Key":"5456","日期":"2014-12-12","科目":"5.支出","項目":"運費-耳機","金額":"80","備註1":"郵局","備註2":"1件","編輯":""},{"Key":"5438","日期":"2014-12-10","科目":"5.支出","項目":"運費-耳機","金額":"190","備註1":"郵局","備註2":"3件","編輯":""},{"Key":"5441","日期":"2014-12-10","科目":"5.支出","項目":"運費-耳機","金額":"185","備註1":"大榮","備註2":"JMPLUSMINI","編輯":""},{"Key":"5431","日期":"2014-12-09","科目":"5.支出","項目":"運費-耳機","金額":"1045","備註1":"大陸快遞","備註2":"耳機盒","編輯":""},{"Key":"5433","日期":"2014-12-09","科目":"5.支出","項目":"運費-耳機","金額":"150","備註1":"郵局","備註2":"2件","編輯":""},{"Key":"5420","日期":"2014-12-08","科目":"5.支出","項目":"運費-耳機","金額":"340","備註1":"郵局","備註2":"8件","編輯":""},{"Key":"5375","日期":"2014-12-03","科目":"5.支出","項目":"運費-耳機","金額":"125","備註1":"郵局","備註2":"3件","編輯":""},{"Key":"5359","日期":"2014-12-02","科目":"5.支出","項目":"運費-耳機","金額":"60","備註1":"7-11","備註2":"1件","編輯":""},{"Key":"5360","日期":"2014-12-02","科目":"5.支出","項目":"運費-耳機","金額":"80","備註1":"郵局","備註2":"1件","編輯":""},{"Key":"5349","日期":"2014-12-01","科目":"5.支出","項目":"運費-耳機","金額":"947","備註1":"郵局","備註2":"7件","編輯":""},{"Key":"5664","日期":"2014-12-30","科目":"5.支出","項目":"雜費","金額":"75","備註1":"光南","備註2":"名片夾+肥皂","編輯":""},{"Key":"5649","日期":"2014-12-29","科目":"5.支出","項目":"雜費","金額":"468","備註1":"傳發","備註2":"吊卡袋","編輯":""},{"Key":"5605","日期":"2014-12-26","科目":"5.支出","項目":"雜費","金額":"3500","備註1":"陳姵妤","備註2":"聖誕裝置","編輯":""},{"Key":"5585","日期":"2014-12-24","科目":"5.支出","項目":"雜費","金額":"1000","備註1":"表框定金","備註2":"","編輯":""},{"Key":"5406","日期":"2014-12-07","科目":"5.支出","項目":"雜費","金額":"550","備註1":"水源市場","備註2":"拜拜水果","編輯":""},{"Key":"5654","日期":"2014-12-30","科目":"5.支出","項目":"電信費","金額":"582","備註1":"0989-650649","備註2":"103-12","編輯":""},{"Key":"5655","日期":"2014-12-30","科目":"5.支出","項目":"電信費","金額":"701","備註1":"0988538527","備註2":"103-12","編輯":""},{"Key":"5656","日期":"2014-12-30","科目":"5.支出","項目":"電信費","金額":"680","備註1":"0963","備註2":"102-11","編輯":""},{"Key":"5657","日期":"2014-12-30","科目":"5.支出","項目":"電信費","金額":"1124","備註1":"29359170","備註2":"103-12","編輯":""},{"Key":"5540","日期":"2014-12-22","科目":"5.支出","項目":"電信費","金額":"840","備註1":"23651207","備註2":"103-11","編輯":""},{"Key":"5541","日期":"2014-12-22","科目":"5.支出","項目":"電信費","金額":"2391","備註1":"23653115","備註2":"103-11","編輯":""},{"Key":"5417","日期":"2014-12-08","科目":"5.支出","項目":"電信費","金額":"682","備註1":"0988538527","備註2":"103-11","編輯":""},{"Key":"5539","日期":"2014-12-22","科目":"5.支出","項目":"電費","金額":"8785","備註1":"台電","備註2":"103-10～12","編輯":""},{"Key":"5686","日期":"2014-12-31","科目":"5.支出","項目":"餐費","金額":"380","備註1":"Lunch","備註2":"3P","編輯":""},{"Key":"5687","日期":"2014-12-31","科目":"5.支出","項目":"餐費","金額":"454","備註1":"Dinner","備註2":"3P","編輯":""},{"Key":"5662","日期":"2014-12-30","科目":"5.支出","項目":"餐費","金額":"360","備註1":"Lunch","備註2":"4P","編輯":""},{"Key":"5663","日期":"2014-12-30","科目":"5.支出","項目":"餐費","金額":"262","備註1":"Dinner","備註2":"3P","編輯":""},{"Key":"5647","日期":"2014-12-29","科目":"5.支出","項目":"餐費","金額":"480","備註1":"Lunch","備註2":"4P","編輯":""},{"Key":"5648","日期":"2014-12-29","科目":"5.支出","項目":"餐費","金額":"420","備註1":"Dinner","備註2":"3P","編輯":""},{"Key":"5638","日期":"2014-12-28","科目":"5.支出","項目":"餐費","金額":"600","備註1":"Lunch","備註2":"5P","編輯":""},{"Key":"5639","日期":"2014-12-28","科目":"5.支出","項目":"餐費","金額":"420","備註1":"Dinner","備註2":"3P","編輯":""},{"Key":"5629","日期":"2014-12-27","科目":"5.支出","項目":"餐費","金額":"600","備註1":"Lunch","備註2":"4P","編輯":""},{"Key":"5630","日期":"2014-12-27","科目":"5.支出","項目":"餐費","金額":"250","備註1":"Dinner","備註2":"3P","編輯":""},{"Key":"5620","日期":"2014-12-26","科目":"5.支出","項目":"餐費","金額":"330","備註1":"Lunch","備註2":"2P","編輯":""},{"Key":"5621","日期":"2014-12-26","科目":"5.支出","項目":"餐費","金額":"400","備註1":"Dinner","備註2":"4P","編輯":""},{"Key":"5610","日期":"2014-12-25","科目":"5.支出","項目":"餐費","金額":"440","備註1":"Lunch","備註2":"4P","編輯":""},{"Key":"5611","日期":"2014-12-25","科目":"5.支出","項目":"餐費","金額":"480","備註1":"Dinner","備註2":"4P","編輯":""},{"Key":"5581","日期":"2014-12-24","科目":"5.支出","項目":"餐費","金額":"660","備註1":"LUNCH","備註2":"6P","編輯":""},{"Key":"5582","日期":"2014-12-24","科目":"5.支出","項目":"餐費","金額":"440","備註1":"DINNER","備註2":"4P","編輯":""},{"Key":"5570","日期":"2014-12-23","科目":"5.支出","項目":"餐費","金額":"470","備註1":"Lunch","備註2":"4P","編輯":""},{"Key":"5571","日期":"2014-12-23","科目":"5.支出","項目":"餐費","金額":"435","備註1":"Dinner","備註2":"3P","編輯":""},{"Key":"5560","日期":"2014-12-22","科目":"5.支出","項目":"餐費","金額":"510","備註1":"Dinner","備註2":"5P","編輯":""},{"Key":"5561","日期":"2014-12-22","科目":"5.支出","項目":"餐費","金額":"480","備註1":"Lunch","備註2":"4P","編輯":""},{"Key":"5535","日期":"2014-12-21","科目":"5.支出","項目":"餐費","金額":"385","備註1":"Lunch","備註2":"4P","編輯":""},{"Key":"5536","日期":"2014-12-21","科目":"5.支出","項目":"餐費","金額":"930","備註1":"Dinner","備註2":"6P","編輯":""},{"Key":"5528","日期":"2014-12-20","科目":"5.支出","項目":"餐費","金額":"300","備註1":"Lunch","備註2":"3P","編輯":""},{"Key":"5529","日期":"2014-12-20","科目":"5.支出","項目":"餐費","金額":"420","備註1":"Dinner","備註2":"3P","編輯":""},{"Key":"5523","日期":"2014-12-19","科目":"5.支出","項目":"餐費","金額":"360","備註1":"Lunch","備註2":"4P","編輯":""},{"Key":"5524","日期":"2014-12-19","科目":"5.支出","項目":"餐費","金額":"900","備註1":"Dinner","備註2":"6P","編輯":""},{"Key":"5512","日期":"2014-12-18","科目":"5.支出","項目":"餐費","金額":"300","備註1":"Lunch","備註2":"4P","編輯":""},{"Key":"5513","日期":"2014-12-18","科目":"5.支出","項目":"餐費","金額":"500","備註1":"Dinner","備註2":"4P","編輯":""},{"Key":"5502","日期":"2014-12-17","科目":"5.支出","項目":"餐費","金額":"440","備註1":"Lunch","備註2":"4P","編輯":""},{"Key":"5503","日期":"2014-12-17","科目":"5.支出","項目":"餐費","金額":"335","備註1":"Dinner","備註2":"4P","編輯":""},{"Key":"5491","日期":"2014-12-16","科目":"5.支出","項目":"餐費","金額":"800","備註1":"Lunch","備註2":"4P","編輯":""},{"Key":"5492","日期":"2014-12-16","科目":"5.支出","項目":"餐費","金額":"610","備註1":"Dinner","備註2":"4P","編輯":""},{"Key":"5481","日期":"2014-12-15","科目":"5.支出","項目":"餐費","金額":"400","備註1":"Lunch","備註2":"4P","編輯":""},{"Key":"5482","日期":"2014-12-15","科目":"5.支出","項目":"餐費","金額":"497","備註1":"Dinner","備註2":"4P","編輯":""},{"Key":"5479","日期":"2014-12-14","科目":"5.支出","項目":"餐費","金額":"850","備註1":"Dinner","備註2":"6P","編輯":""},{"Key":"5462","日期":"2014-12-13","科目":"5.支出","項目":"餐費","金額":"380","備註1":"Lunch","備註2":"4P","編輯":""},{"Key":"5463","日期":"2014-12-13","科目":"5.支出","項目":"餐費","金額":"1220","備註1":"Dinner","備註2":"4P","編輯":""},{"Key":"5445","日期":"2014-12-12","科目":"5.支出","項目":"餐費","金額":"440","備註1":"Lunch","備註2":"4P","編輯":""},{"Key":"5446","日期":"2014-12-12","科目":"5.支出","項目":"餐費","金額":"395","備註1":"Dinner","備註2":"3P","編輯":""},{"Key":"5454","日期":"2014-12-12","科目":"5.支出","項目":"餐費","金額":"300","備註1":"Lunch","備註2":"4P","編輯":""},{"Key":"5455","日期":"2014-12-12","科目":"5.支出","項目":"餐費","金額":"347","備註1":"Dinner","備註2":"4P","編輯":""},{"Key":"5439","日期":"2014-12-10","科目":"5.支出","項目":"餐費","金額":"460","備註1":"Lunch","備註2":"4P","編輯":""},{"Key":"5440","日期":"2014-12-10","科目":"5.支出","項目":"餐費","金額":"530","備註1":"Dinner","備註2":"5P","編輯":""},{"Key":"5429","日期":"2014-12-09","科目":"5.支出","項目":"餐費","金額":"340","備註1":"Lunch","備註2":"4P","編輯":""},{"Key":"5430","日期":"2014-12-09","科目":"5.支出","項目":"餐費","金額":"300","備註1":"Dinner","備註2":"","編輯":""},{"Key":"5418","日期":"2014-12-08","科目":"5.支出","項目":"餐費","金額":"500","備註1":"Lunch","備註2":"4P","編輯":""},{"Key":"5419","日期":"2014-12-08","科目":"5.支出","項目":"餐費","金額":"270","備註1":"Dinner","備註2":"3P","編輯":""},{"Key":"5404","日期":"2014-12-07","科目":"5.支出","項目":"餐費","金額":"435","備註1":"Lunch","備註2":"5P","編輯":""},{"Key":"5405","日期":"2014-12-07","科目":"5.支出","項目":"餐費","金額":"1175","備註1":"Dinner","備註2":"6P","編輯":""},{"Key":"5394","日期":"2014-12-06","科目":"5.支出","項目":"餐費","金額":"340","備註1":"Lunch","備註2":"3P","編輯":""},{"Key":"5395","日期":"2014-12-06","科目":"5.支出","項目":"餐費","金額":"320","備註1":"Dinner","備註2":"4P","編輯":""},{"Key":"5388","日期":"2014-12-05","科目":"5.支出","項目":"餐費","金額":"320","備註1":"Lunch","備註2":"4P","編輯":""},{"Key":"5389","日期":"2014-12-05","科目":"5.支出","項目":"餐費","金額":"300","備註1":"Dinner","備註2":"3P","編輯":""},{"Key":"5379","日期":"2014-12-04","科目":"5.支出","項目":"餐費","金額":"460","備註1":"Lunch","備註2":"4P","編輯":""},{"Key":"5380","日期":"2014-12-04","科目":"5.支出","項目":"餐費","金額":"626","備註1":"Dinner","備註2":"4P","編輯":""},{"Key":"5374","日期":"2014-12-03","科目":"5.支出","項目":"餐費","金額":"430","備註1":"Lunch","備註2":"4P","編輯":""},{"Key":"5357","日期":"2014-12-02","科目":"5.支出","項目":"餐費","金額":"428","備註1":"Lunch","備註2":"4P","編輯":""},{"Key":"5358","日期":"2014-12-02","科目":"5.支出","項目":"餐費","金額":"479","備註1":"Dinner","備註2":"3P","編輯":""},{"Key":"5346","日期":"2014-12-01","科目":"5.支出","項目":"餐費","金額":"450","備註1":"Lunch","備註2":"4P","編輯":""},{"Key":"5347","日期":"2014-12-01","科目":"5.支出","項目":"餐費","金額":"270","備註1":"Dinner","備註2":"3P","編輯":""},{"Key":"5624","日期":"2014-12-29","科目":"6.銀支","項目":"貨款-耳機","金額":"14648","備註1":"電光火石","備註2":"進貨單號:2736,2533","編輯":""},{"Key":"5640","日期":"2014-12-29","科目":"6.銀支","項目":"貨款-耳機","金額":"15700","備註1":"偉商","備註2":"進貨單號:2748,2696","編輯":""},{"Key":"5641","日期":"2014-12-29","科目":"6.銀支","項目":"貨款-耳機","金額":"4200","備註1":"將門廣告","備註2":"進貨單號:2802","編輯":""},{"Key":"5615","日期":"2014-12-26","科目":"6.銀支","項目":"貨款-耳機","金額":"7398","備註1":"尼恩","備註2":"進貨單號:2827","編輯":""},{"Key":"5576","日期":"2014-12-24","科目":"6.銀支","項目":"貨款-耳機","金額":"9579","備註1":"尼恩","備註2":"進貨單號:2761,2738","編輯":""},{"Key":"5537","日期":"2014-12-22","科目":"6.銀支","項目":"貨款-耳機","金額":"10800","備註1":"黑曜石","備註2":"進貨單號:2803,2804","編輯":""},{"Key":"5106","日期":"2014-12-15","科目":"6.銀支","項目":"貨款-耳機","金額":"22450","備註1":"台灣山葉","備註2":"進貨單號:2478","編輯":""},{"Key":"5467","日期":"2014-12-15","科目":"6.銀支","項目":"貨款-耳機","金額":"651672","備註1":"Sony","備註2":"進貨單號:2684,2678,2667,2662,2653,2649,2647,2636,2619,2620,2612,2600,2585,2591,2571","編輯":""},{"Key":"5424","日期":"2014-12-10","科目":"6.銀支","項目":"貨款-耳機","金額":"30585","備註1":"偉商","備註2":"進貨單號:2666,2631,2632,2566","編輯":""},{"Key":"5362","日期":"2014-12-03","科目":"6.銀支","項目":"貨款-耳機","金額":"19540","備註1":"聚勝","備註2":"進貨單號:2704","編輯":""},{"Key":"5353","日期":"2014-12-02","科目":"6.銀支","項目":"貨款-耳機","金額":"10570","備註1":"尼恩","備註2":"進貨單號:2691","編輯":""},{"Key":"5132","日期":"2014-12-01","科目":"6.銀支","項目":"貨款-耳機","金額":"16064","備註1":"AKG","備註2":"進貨單號:2516,2501","編輯":""},{"Key":"5073","日期":"2014-12-31","科目":"8.票支","項目":"貨款-耳機","金額":"51730","備註1":"永聖","備註2":"736","編輯":""},{"Key":"5226","日期":"2014-12-31","科目":"8.票支","項目":"貨款-耳機","金額":"143820","備註1":"永聖","備註2":"760","編輯":""},{"Key":"5228","日期":"2014-12-31","科目":"8.票支","項目":"貨款-耳機","金額":"50400","備註1":"統一數位","備註2":"762","編輯":""},{"Key":"5229","日期":"2014-12-31","科目":"8.票支","項目":"貨款-耳機","金額":"420","備註1":"統一數位","備註2":"763","編輯":""},{"Key":"5230","日期":"2014-12-31","科目":"8.票支","項目":"貨款-耳機","金額":"22205","備註1":"思維","備註2":"764","編輯":""},{"Key":"5280","日期":"2014-12-31","科目":"8.票支","項目":"貨款-耳機","金額":"334520","備註1":"宙宣","備註2":"767","編輯":""},{"Key":"5363","日期":"2014-12-31","科目":"8.票支","項目":"貨款-耳機","金額":"34020","備註1":"富銘","備註2":"769","編輯":""},{"Key":"5364","日期":"2014-12-31","科目":"8.票支","項目":"貨款-耳機","金額":"348615","備註1":"富銘","備註2":"770","編輯":""},{"Key":"5365","日期":"2014-12-31","科目":"8.票支","項目":"貨款-耳機","金額":"55400","備註1":"CHORD","備註2":"771","編輯":""},{"Key":"5367","日期":"2014-12-31","科目":"8.票支","項目":"貨款-耳機","金額":"73465","備註1":"鍵寧","備註2":"772","編輯":""},{"Key":"5465","日期":"2014-12-31","科目":"8.票支","項目":"貨款-耳機","金額":"76590","備註1":"鈦孚","備註2":"782","編輯":""},{"Key":"5472","日期":"2014-12-31","科目":"8.票支","項目":"貨款-耳機","金額":"9900","備註1":"迎家音響","備註2":"787","編輯":""},{"Key":"5473","日期":"2014-12-31","科目":"8.票支","項目":"貨款-耳機","金額":"326895","備註1":"鼎恆","備註2":"788","編輯":""},{"Key":"5595","日期":"2014-12-31","科目":"8.票支","項目":"貨款-耳機","金額":"37500","備註1":"勝旗","備註2":"793","編輯":""},{"Key":"5601","日期":"2014-12-31","科目":"8.票支","項目":"貨款-耳機","金額":"77715","備註1":"世貨","備註2":"799","編輯":""},{"Key":"5602","日期":"2014-12-31","科目":"8.票支","項目":"貨款-耳機","金額":"195772","備註1":"宙宣","備註2":"800","編輯":""},{"Key":"5603","日期":"2014-12-31","科目":"8.票支","項目":"貨款-耳機","金額":"65000","備註1":"管迷","備註2":"801","編輯":""},{"Key":"5604","日期":"2014-12-31","科目":"8.票支","項目":"貨款-耳機","金額":"123220","備註1":"皇佳","備註2":"802","編輯":""},{"Key":"5466","日期":"2014-12-15","科目":"8.票支","項目":"貨款-耳機","金額":"12587","備註1":"先鋒","備註2":"783","編輯":""}]